{"version":1,"source":"indexeddb-geo2025-snapshot","modified":1782096381181,"work":{"id":266663,"cn":"孤独的美食家 2018除夕特别篇 京都·名古屋出差篇","title":"孤独のグルメ 大晦日スペシャル 京都・名古屋出張編","cover":"http://bgm-api.anitabi.cn/pic/cover/l/b3/3d/266663_PyYNW.jpg","fade":7.7,"cat":"日剧","points":[{"id":"d2d2753c","geo":[35.02563,135.794938],"priority":238,"name":"梨門邸","isFolder":false,"folder":"京都府京都市的方头鱼火锅饭","mid":"1qmw6xKlLpQS6H5Yt5PaaUP6YzAfjq4E","image":"/images/points/266663/d2d2753c_1741376392125.jpg","s":476,"mark":"〒606-8405京都市左京区浄土時上南田町37","density":123297,"origin":"Google My Maps","originURL":"https://www.google.com/maps/d/viewer?mid=1qmw6xKlLpQS6H5Yt5PaaUP6YzAfjq4E&ll=35.02563%2C135.794938"},{"id":"18909931","geo":[35.166051,136.896806],"priority":384,"name":"カラス","cn":"喫茶カラス","isFolder":false,"folder":"名古屋早点套餐：综合咖啡和豆沙吐司","mid":"1qmw6xKlLpQS6H5Yt5PaaUP6YzAfjq4E","image":"/images/points/266663/18909931_1741376415018.jpg","s":1815,"mark":"〒460-0008名古屋市中区栄1-12-2","density":7148,"origin":"Google My Maps","originURL":"https://www.google.com/maps/d/viewer?mid=1qmw6xKlLpQS6H5Yt5PaaUP6YzAfjq4E&ll=35.166051%2C136.896806"},{"id":"f503f155","geo":[35.230446,136.897384],"priority":4952,"name":"ＪＭヒラ","cn":"台湾ラーメン光陽","isFolder":false,"folder":"爱知县名古屋市的台湾拉面","mid":"1qmw6xKlLpQS6H5Yt5PaaUP6YzAfjq4E","image":"/images/points/266663/f503f155_1741376510908.jpg","s":2486,"mark":"〒452-0802名古屋市西区比良3-139","density":7148,"origin":"Google My Maps","originURL":"https://www.google.com/maps/d/viewer?mid=1qmw6xKlLpQS6H5Yt5PaaUP6YzAfjq4E&ll=35.230446%2C136.897384"}],"tags":[],"priority":999,"icon":null,"theme":{"src":"/images/ptheme/266663_100_76.webp?v=ha28u","ids":["d2d2753c","18909931","f503f155"],"modified":1741376530040,"w":100,"h":76},"modified":1741539835565,"pointsLength":3,"imagesLength":3},"points":[{"id":"d2d2753c","geo":[35.02563,135.794938],"priority":238,"name":"梨門邸","isFolder":false,"folder":"京都府京都市的方头鱼火锅饭","mid":"1qmw6xKlLpQS6H5Yt5PaaUP6YzAfjq4E","image":"/images/points/266663/d2d2753c_1741376392125.jpg","s":476,"mark":"〒606-8405京都市左京区浄土時上南田町37","density":123297,"origin":"Google My Maps","originURL":"https://www.google.com/maps/d/viewer?mid=1qmw6xKlLpQS6H5Yt5PaaUP6YzAfjq4E&ll=35.02563%2C135.794938"},{"id":"18909931","geo":[35.166051,136.896806],"priority":384,"name":"カラス","cn":"喫茶カラス","isFolder":false,"folder":"名古屋早点套餐：综合咖啡和豆沙吐司","mid":"1qmw6xKlLpQS6H5Yt5PaaUP6YzAfjq4E","image":"/images/points/266663/18909931_1741376415018.jpg","s":1815,"mark":"〒460-0008名古屋市中区栄1-12-2","density":7148,"origin":"Google My Maps","originURL":"https://www.google.com/maps/d/viewer?mid=1qmw6xKlLpQS6H5Yt5PaaUP6YzAfjq4E&ll=35.166051%2C136.896806"},{"id":"f503f155","geo":[35.230446,136.897384],"priority":4952,"name":"ＪＭヒラ","cn":"台湾ラーメン光陽","isFolder":false,"folder":"爱知县名古屋市的台湾拉面","mid":"1qmw6xKlLpQS6H5Yt5PaaUP6YzAfjq4E","image":"/images/points/266663/f503f155_1741376510908.jpg","s":2486,"mark":"〒452-0802名古屋市西区比良3-139","density":7148,"origin":"Google My Maps","originURL":"https://www.google.com/maps/d/viewer?mid=1qmw6xKlLpQS6H5Yt5PaaUP6YzAfjq4E&ll=35.230446%2C136.897384"}]}