{"version":1,"source":"indexeddb-geo2025-snapshot","modified":1782096381181,"work":{"id":372010,"cn":"狼与香辛料 行商邂逅贤狼","title":"狼と香辛料 MERCHANT MEETS THE WISE WOLF","city":"欧洲","color":"#bf8d5d","cover":"/images/bangumi/372010.jpg","fade":7.5,"cat":"TV","geo":[43.768795,11.256424],"zoom":14.5,"points":[{"id":"k7r0jcmey","geo":[43.768422,11.253628],"priority":25,"name":"Via dei Girolami","cn":"吉罗拉米路","isFolder":false,"uid":1058,"image":"/images/user/1058/bangumi/372010/points/k7r0jcmey-1715173659301.jpg","ep":3,"s":964,"density":868,"origin":"@Eureka","originURL":""},{"id":"k7rn7um5t","geo":[43.768892,11.261436],"priority":425,"name":"Piazza di Santa Croce","cn":"圣十字广场","isFolder":false,"uid":1058,"image":"/images/user/1058/bangumi/372010/points/k7rn7um5t-1715174215847.jpg","ep":3,"s":190,"density":868,"origin":"@Eureka","originURL":""},{"id":"o3nnb9d1x","geo":[48.856687,2.346778],"priority":46,"name":"Pont au Change","cn":"兑换桥","isFolder":false,"image":"/images/user/0/bangumi/372010/points/o3nnb9d1x-1726136466047.jpg","ep":3,"s":1003,"origin":"费城飞蓬","originURL":""},{"id":"cm7ldpi","geo":[43.768229,11.254027],"priority":25,"name":"Lungarno degli Archibusieri","isFolder":false,"image":"/images/user/0/bangumi/372010/points/cm7ldpi-1774474833099.jpg","ep":3,"s":1009,"origin":"@沧沐Soumoku","originURL":""},{"id":"cm7psue","geo":[43.767789,11.25525],"priority":8,"name":"乌菲兹美术馆前拱廊","isFolder":false,"image":"/images/user/0/bangumi/372010/points/cm7psue-1774474967724.jpg","ep":3,"s":924,"origin":"@沧沐Soumoku","originURL":""},{"id":"cm7tqnp","geo":[43.767131,11.254308],"priority":121,"name":"阿诺河沿岸（往对面看）","isFolder":false,"image":"/images/user/0/bangumi/372010/points/cm7tqnp-1774475161446.jpg","ep":3,"s":981,"origin":"@沧沐Soumoku","originURL":""},{"id":"cm7vfh3","geo":[43.77421,11.249501],"priority":37,"name":"圣十字圣殿","isFolder":false,"image":"/images/user/0/bangumi/372010/points/cm7vfh3-1774475240760.jpg","ep":3,"s":184,"mark":"经实地考据，剧中的教堂与新圣母圣殿更加相像，尤其是广场的塔柱完美复刻。","origin":"@沧沐Soumoku","originURL":""},{"id":"cm7wnm4","geo":[43.768338,11.25383],"priority":164,"name":"Piazza del Pesce","isFolder":false,"image":"/images/user/0/bangumi/372010/points/cm7wnm4-1777136780066.jpg","ep":3,"s":944,"origin":"@沧沐Soumoku","originURL":""},{"id":"cm8dkx5","geo":[43.766193,11.258726],"priority":431,"name":"Ponte alle Grazie","isFolder":false,"image":"/images/user/0/bangumi/372010/points/cm8dkx5-1774476077664.jpg","ep":3,"s":1253,"mark":"比起之前同好所上传的法国兑换桥，这里的位置以及取景可能更加合理。","origin":"@沧沐Soumoku","originURL":""},{"id":"du8ac9s","geo":[43.773886,11.24954],"priority":23,"name":"新圣母圣殿","isFolder":false,"image":"/images/user/0/bangumi/372010/points/du8ac9s-1777136459214.jpg","ep":3,"s":187,"mark":"比起之前打点的圣十字圣殿，此建筑的外观以及尖塔更加符合原著。","origin":"沧沐Soumoku","originURL":""},{"id":"du8dl7u","geo":[43.773576,11.249423],"priority":21,"name":"Piazza di Santa Maria Novella","isFolder":false,"image":"/images/user/0/bangumi/372010/points/du8dl7u-1777136587064.jpg","ep":3,"s":181,"origin":"","originURL":""},{"id":"du8ftlb","geo":[43.768147,11.255316],"priority":45,"name":"乌菲兹美术馆拱廊","isFolder":false,"image":"/images/user/0/bangumi/372010/points/du8ftlb-1777136696163.jpg","ep":3,"s":902,"origin":"","originURL":""},{"id":"du8gqpp","geo":[43.76777,11.255187],"priority":906,"name":"乌菲兹美术馆前拱廊","isFolder":false,"image":"/images/user/0/bangumi/372010/points/du8gqpp-1777136729134.jpg","ep":3,"s":932,"origin":"","originURL":""},{"id":"du8i9w5","geo":[43.773687,11.249565],"priority":94839,"name":"新圣母大殿","isFolder":false,"image":"/images/user/0/bangumi/372010/points/du8i9w5-1777136808366.jpg","ep":3,"s":217,"origin":"","originURL":""}],"tags":[],"priority":220659,"icon":"/images/icon/372010.jpg","tAbbr":"狼と香辛料","modified":1777904492870,"pointsLength":14,"imagesLength":14},"points":[{"id":"k7r0jcmey","geo":[43.768422,11.253628],"priority":25,"name":"Via dei Girolami","cn":"吉罗拉米路","isFolder":false,"uid":1058,"image":"/images/user/1058/bangumi/372010/points/k7r0jcmey-1715173659301.jpg","ep":3,"s":964,"density":868,"origin":"@Eureka","originURL":""},{"id":"k7rn7um5t","geo":[43.768892,11.261436],"priority":425,"name":"Piazza di Santa Croce","cn":"圣十字广场","isFolder":false,"uid":1058,"image":"/images/user/1058/bangumi/372010/points/k7rn7um5t-1715174215847.jpg","ep":3,"s":190,"density":868,"origin":"@Eureka","originURL":""},{"id":"o3nnb9d1x","geo":[48.856687,2.346778],"priority":46,"name":"Pont au Change","cn":"兑换桥","isFolder":false,"image":"/images/user/0/bangumi/372010/points/o3nnb9d1x-1726136466047.jpg","ep":3,"s":1003,"origin":"费城飞蓬","originURL":""},{"id":"cm7ldpi","geo":[43.768229,11.254027],"priority":25,"name":"Lungarno degli Archibusieri","isFolder":false,"image":"/images/user/0/bangumi/372010/points/cm7ldpi-1774474833099.jpg","ep":3,"s":1009,"origin":"@沧沐Soumoku","originURL":""},{"id":"cm7psue","geo":[43.767789,11.25525],"priority":8,"name":"乌菲兹美术馆前拱廊","isFolder":false,"image":"/images/user/0/bangumi/372010/points/cm7psue-1774474967724.jpg","ep":3,"s":924,"origin":"@沧沐Soumoku","originURL":""},{"id":"cm7tqnp","geo":[43.767131,11.254308],"priority":121,"name":"阿诺河沿岸（往对面看）","isFolder":false,"image":"/images/user/0/bangumi/372010/points/cm7tqnp-1774475161446.jpg","ep":3,"s":981,"origin":"@沧沐Soumoku","originURL":""},{"id":"cm7vfh3","geo":[43.77421,11.249501],"priority":37,"name":"圣十字圣殿","isFolder":false,"image":"/images/user/0/bangumi/372010/points/cm7vfh3-1774475240760.jpg","ep":3,"s":184,"mark":"经实地考据，剧中的教堂与新圣母圣殿更加相像，尤其是广场的塔柱完美复刻。","origin":"@沧沐Soumoku","originURL":""},{"id":"cm7wnm4","geo":[43.768338,11.25383],"priority":164,"name":"Piazza del Pesce","isFolder":false,"image":"/images/user/0/bangumi/372010/points/cm7wnm4-1777136780066.jpg","ep":3,"s":944,"origin":"@沧沐Soumoku","originURL":""},{"id":"cm8dkx5","geo":[43.766193,11.258726],"priority":431,"name":"Ponte alle Grazie","isFolder":false,"image":"/images/user/0/bangumi/372010/points/cm8dkx5-1774476077664.jpg","ep":3,"s":1253,"mark":"比起之前同好所上传的法国兑换桥，这里的位置以及取景可能更加合理。","origin":"@沧沐Soumoku","originURL":""},{"id":"du8ac9s","geo":[43.773886,11.24954],"priority":23,"name":"新圣母圣殿","isFolder":false,"image":"/images/user/0/bangumi/372010/points/du8ac9s-1777136459214.jpg","ep":3,"s":187,"mark":"比起之前打点的圣十字圣殿，此建筑的外观以及尖塔更加符合原著。","origin":"沧沐Soumoku","originURL":""},{"id":"du8dl7u","geo":[43.773576,11.249423],"priority":21,"name":"Piazza di Santa Maria Novella","isFolder":false,"image":"/images/user/0/bangumi/372010/points/du8dl7u-1777136587064.jpg","ep":3,"s":181,"origin":"","originURL":""},{"id":"du8ftlb","geo":[43.768147,11.255316],"priority":45,"name":"乌菲兹美术馆拱廊","isFolder":false,"image":"/images/user/0/bangumi/372010/points/du8ftlb-1777136696163.jpg","ep":3,"s":902,"origin":"","originURL":""},{"id":"du8gqpp","geo":[43.76777,11.255187],"priority":906,"name":"乌菲兹美术馆前拱廊","isFolder":false,"image":"/images/user/0/bangumi/372010/points/du8gqpp-1777136729134.jpg","ep":3,"s":932,"origin":"","originURL":""},{"id":"du8i9w5","geo":[43.773687,11.249565],"priority":94839,"name":"新圣母大殿","isFolder":false,"image":"/images/user/0/bangumi/372010/points/du8i9w5-1777136808366.jpg","ep":3,"s":217,"origin":"","originURL":""}]}