{"version":1,"source":"indexeddb-geo2025-snapshot","modified":1782096381181,"work":{"id":525565,"cn":"相反的你和我","title":"正反対な君と僕","city":"横滨市","color":"#ee00ff","cover":"/images/bangumi/525565_fej6i2c.jpg","fade":7.5,"cat":"TV","points":[{"id":"9pfzgls","geo":[35.560983,139.552905],"priority":3,"name":"赤田東公園 西侧","isFolder":false,"folder":"赤田东公园-横滨市","uid":2168,"image":"/images/points/525565/9pfzgls_1768139902256.jpg","ep":1,"s":"","density":2,"origin":"@甜食伯爵","originURL":""},{"id":"9pft9x1","geo":[35.561076,139.552899],"priority":4,"name":"赤田東公園 西侧","isFolder":false,"folder":"赤田东公园-横滨市","uid":2168,"image":"/images/points/525565/9pft9x1_1768139611532.jpg","ep":1,"s":"","density":3,"origin":"@甜食伯爵","originURL":""},{"id":"9pfs2jc","geo":[35.560859,139.552866],"priority":3,"name":"赤田東公園 西侧","isFolder":false,"folder":"赤田东公园-横滨市","uid":2168,"image":"/images/points/525565/9pfs2jc_1768139574187.jpg","ep":1,"s":"","density":3,"origin":"@甜食伯爵","originURL":""},{"id":"9pfxqz3","geo":[35.560831,139.552792],"priority":4,"name":"赤田東公園 西侧","isFolder":false,"folder":"赤田东公园-横滨市","uid":2168,"image":"/images/points/525565/9pfxqz3_1768139821039.jpg","ep":1,"s":"","density":4,"origin":"@甜食伯爵","originURL":""},{"id":"9pftujr","geo":[35.561015,139.552863],"priority":3,"name":"赤田東公園 西侧","isFolder":false,"folder":"赤田东公园-横滨市","uid":2168,"image":"/images/points/525565/9pftujr_1768139668899.jpg","ep":1,"s":"","density":3,"origin":"@甜食伯爵","originURL":""},{"id":"9pfwyfr","geo":[35.560922,139.552794],"priority":4,"name":"赤田東公園 西侧","isFolder":false,"folder":"赤田东公园-横滨市","uid":2168,"image":"/images/points/525565/9pfwyfr_1768139809568.jpg","ep":1,"s":"","density":4,"origin":"@甜食伯爵","originURL":""},{"id":"9pfxxtv","geo":[35.560884,139.552869],"priority":4,"name":"赤田東公園 西侧","isFolder":false,"folder":"赤田东公园-横滨市","uid":2168,"image":"/images/points/525565/9pfxxtv_1768139835273.jpg","ep":1,"s":"","density":3,"origin":"@甜食伯爵","originURL":""},{"id":"9pfznkl","geo":[35.560988,139.552861],"priority":3,"name":"赤田東公園 西侧","isFolder":false,"folder":"赤田东公园-横滨市","uid":2168,"image":"/images/points/525565/9pfznkl_1768139909012.jpg","ep":1,"s":"","density":2,"origin":"@甜食伯爵","originURL":""},{"id":"9pftmp3","geo":[35.561115,139.552907],"priority":4,"name":"赤田東公園 西侧","isFolder":false,"folder":"赤田东公园-横滨市","uid":2168,"image":"/images/points/525565/9pftmp3_1768139630558.jpg","ep":1,"s":"","density":4,"origin":"@甜食伯爵","originURL":""},{"id":"9pfzz2g","geo":[35.56104,139.552928],"priority":4,"name":"赤田東公園 西侧","isFolder":false,"folder":"赤田东公园-横滨市","uid":2168,"image":"/images/points/525565/9pfzz2g_1768139928830.jpg","ep":1,"s":"","density":3,"origin":"@甜食伯爵","originURL":""},{"id":"9pg0qh3","geo":[35.560918,139.552844],"priority":3,"name":"赤田東公園 西侧","isFolder":false,"folder":"赤田东公园-横滨市","uid":2168,"image":"/images/points/525565/9pg0qh3_1768139958244.jpg","ep":1,"s":"","density":3,"origin":"@甜食伯爵","originURL":""},{"id":"9pfuo2q","geo":[35.561048,139.552895],"priority":4,"name":"赤田東公園 西侧","isFolder":false,"folder":"赤田东公园-横滨市","uid":2168,"image":"/images/points/525565/9pfuo2q_1768139677315.jpg","ep":1,"s":"","density":3,"origin":"@甜食伯爵","originURL":""},{"id":"9pfz21w","geo":[35.560912,139.552872],"priority":5,"name":"赤田東公園 西侧","isFolder":false,"folder":"赤田东公园-横滨市","uid":2168,"image":"/images/points/525565/9pfz21w_1768139879478.jpg","ep":1,"s":"","density":3,"origin":"@甜食伯爵","originURL":""},{"id":"9pftfnv","geo":[35.561078,139.552863],"priority":5,"name":"赤田東公園 西侧","isFolder":false,"folder":"赤田东公园-横滨市","uid":2168,"image":"/images/points/525565/9pftfnv_1768139621177.jpg","ep":1,"s":"","density":4,"origin":"@甜食伯爵","originURL":""},{"id":"9pft26j","geo":[35.560955,139.552849],"priority":4,"name":"赤田東公園 西侧","isFolder":false,"folder":"赤田东公园-横滨市","uid":2168,"image":"/images/points/525565/9pft26j_1768139601828.jpg","ep":1,"s":"","density":4,"origin":"@甜食伯爵","originURL":""},{"id":"9pfyrzs","geo":[35.560943,139.552904],"priority":3,"name":"赤田東公園 西侧","isFolder":false,"folder":"赤田东公园-横滨市","uid":2168,"image":"/images/points/525565/9pfyrzs_1768139874177.jpg","ep":1,"s":"","density":3,"origin":"@甜食伯爵","originURL":""},{"id":"9pfxb76","geo":[35.560926,139.552759],"priority":10,"name":"赤田東公園 西侧","isFolder":false,"folder":"赤田东公园-横滨市","uid":2168,"image":"/images/points/525565/9pfxb76_1768139802501.jpg","ep":1,"s":"","density":4,"origin":"@甜食伯爵","originURL":""},{"id":"9pfu6q8","geo":[35.561012,139.552929],"priority":4,"name":"赤田東公園 西侧","isFolder":false,"folder":"赤田东公园-横滨市","uid":2168,"image":"/images/points/525565/9pfu6q8_1768139657609.jpg","ep":1,"s":"","density":3,"origin":"@甜食伯爵","originURL":""},{"id":"9pfrhg5","geo":[35.560861,139.55283],"priority":4,"name":"赤田東公園 西侧","isFolder":false,"folder":"赤田东公园-横滨市","uid":2168,"image":"/images/points/525565/9pfrhg5_1768139536469.jpg","ep":1,"s":"","density":4,"origin":"@甜食伯爵","originURL":""},{"id":"9pfuv03","geo":[35.561094,139.552932],"priority":3,"name":"赤田東公園 西侧","isFolder":false,"folder":"赤田东公园-横滨市","uid":2168,"image":"/images/points/525565/9pfuv03_1768139683345.jpg","ep":1,"s":"","density":2,"origin":"@甜食伯爵","originURL":""},{"id":"9pfrvkl","geo":[35.560829,139.552826],"priority":5,"name":"赤田東公園 西侧","isFolder":false,"folder":"赤田东公园-横滨市","uid":2168,"image":"/images/points/525565/9pfrvkl_1768139545436.jpg","ep":1,"s":"","density":4,"origin":"@甜食伯爵","originURL":""},{"id":"9pfy8go","geo":[35.560892,139.552839],"priority":7,"name":"赤田東公園 西侧","isFolder":false,"folder":"赤田东公园-横滨市","uid":2168,"image":"/images/points/525565/9pfy8go_1768139843420.jpg","ep":1,"s":"","density":3,"origin":"@甜食伯爵","originURL":""},{"id":"9pfyf6f","geo":[35.560822,139.552891],"priority":4,"name":"赤田東公園 西侧","isFolder":false,"folder":"赤田东公园-横滨市","uid":2168,"image":"/images/points/525565/9pfyf6f_1768139853281.jpg","ep":1,"s":"","density":3,"origin":"@甜食伯爵","originURL":""},{"id":"9pfylrt","geo":[35.560869,139.552895],"priority":7,"name":"赤田東公園 西侧","isFolder":false,"folder":"赤田东公园-横滨市","uid":2168,"image":"/images/points/525565/9pfylrt_1768139860104.jpg","ep":1,"s":"","density":3,"origin":"@甜食伯爵","originURL":""},{"id":"9pfzsrc","geo":[35.560981,139.552926],"priority":6,"name":"赤田東公園 西侧","isFolder":false,"folder":"赤田东公园-横滨市","uid":2168,"image":"/images/points/525565/9pfzsrc_1768139916917.jpg","ep":1,"s":"","density":2,"origin":"@甜食伯爵","originURL":""},{"id":"9pfz67i","geo":[35.560984,139.55288],"priority":4,"name":"赤田東公園 西侧","isFolder":false,"folder":"赤田东公园-横滨市","uid":2168,"image":"/images/points/525565/9pfz67i_1768139889024.jpg","ep":1,"s":"","density":2,"origin":"@甜食伯爵","originURL":""},{"id":"9pg08wr","geo":[35.561038,139.552868],"priority":8,"name":"赤田東公園 西侧","isFolder":false,"folder":"赤田东公园-横滨市","uid":2168,"image":"/images/points/525565/9pg08wr_1768139941751.jpg","ep":1,"s":"","density":3,"origin":"@甜食伯爵","originURL":""},{"id":"9pfsc64","geo":[35.560823,139.552863],"priority":15,"name":"赤田東公園 西侧","isFolder":false,"folder":"赤田东公园-横滨市","uid":2168,"image":"/images/points/525565/9pfsc64_1768139567767.jpg","ep":1,"s":"","density":3,"origin":"@甜食伯爵","originURL":""},{"id":"9pg0inw","geo":[35.561073,139.552929],"priority":15,"name":"赤田東公園 西侧","isFolder":false,"folder":"赤田东公园-横滨市","uid":2168,"image":"/images/points/525565/9pg0inw_1768139950751.jpg","ep":1,"s":"","density":2,"origin":"@甜食伯爵","originURL":""},{"id":"9pfsmq9","geo":[35.560949,139.55288],"priority":132,"name":"赤田東公園 西侧","isFolder":false,"folder":"赤田东公园-横滨市","uid":2168,"image":"/images/points/525565/9pfsmq9_1768139581918.jpg","ep":1,"s":"","density":3,"origin":"@甜食伯爵","originURL":""},{"id":"9pfv6rb","geo":[35.562179,139.553098],"priority":6,"name":"赤田東公園 西北角","isFolder":false,"folder":"赤田东公园-横滨市","uid":2168,"image":"/images/points/525565/9pfv6rb_1768139705264.jpg","ep":1,"s":"","density":5,"origin":"@甜食伯爵","originURL":""},{"id":"9pfwn6r","geo":[35.562116,139.553087],"priority":13,"name":"赤田東公園 西北角","isFolder":false,"folder":"赤田东公园-横滨市","uid":2168,"image":"/images/points/525565/9pfwn6r_1768139766736.jpg","ep":1,"s":"","density":7,"origin":"@甜食伯爵","originURL":""},{"id":"9pfvglu","geo":[35.562344,139.55313],"priority":5,"name":"赤田東公園 西北角","isFolder":false,"folder":"赤田东公园-横滨市","uid":2168,"image":"/images/points/525565/9pfvglu_1768139714128.jpg","ep":1,"s":"","density":5,"origin":"@甜食伯爵","originURL":""},{"id":"9pfvrva","geo":[35.562386,139.55313],"priority":18,"name":"赤田東公園 西北角","isFolder":false,"folder":"赤田东公园-横滨市","uid":2168,"image":"/images/points/525565/9pfvrva_1768139727705.jpg","ep":1,"s":"","density":5,"origin":"@甜食伯爵","originURL":""},{"id":"9pfvmkw","geo":[35.562226,139.553104],"priority":410,"name":"赤田東公園 西北角","isFolder":false,"folder":"赤田东公园-横滨市","uid":2168,"image":"/images/points/525565/9pfvmkw_1768139719531.jpg","ep":1,"s":"","density":5,"origin":"@甜食伯爵","originURL":""},{"id":"9pbyi5r","geo":[35.471957,139.610327],"priority":21,"name":"神奈川県立横浜翠嵐高等学校 正门","isFolder":false,"folder":"翠岚高-横滨市","uid":2168,"image":"/images/points/525565/9pbyi5r_1768134471915.jpg","ep":1,"s":"","mark":"【此处属于学校地产，未经许可请勿入内】学院原型与取材地，神奈川县最好的公立学校，偏差值75，全国第23位。","density":20,"origin":"@甜食伯爵","originURL":""},{"id":"9pdnslh","geo":[35.47219,139.610355],"priority":9,"name":"神奈川県立横浜翠嵐高等学校 正门","isFolder":false,"folder":"翠岚高-横滨市","uid":2168,"image":"/images/points/525565/9pdnslh_1768135996330.jpg","ep":1,"s":"","mark":"【此处属于学校地产，未经许可请勿入内】学院原型与取材地，神奈川县最好的公立学校，偏差值75，全国第23位。","density":8,"origin":"@甜食伯爵","originURL":""},{"id":"9pe1jh9","geo":[35.472169,139.610275],"priority":11,"name":"神奈川県立横浜翠嵐高等学校 正门","isFolder":false,"folder":"翠岚高-横滨市","uid":2168,"image":"/images/points/525565/9pe1jh9_1768136642710.jpg","ep":1,"s":"","mark":"【此处属于学校地产，未经许可请勿入内】学院原型与取材地，神奈川县最好的公立学校，偏差值75，全国第23位。","density":9,"origin":"@甜食伯爵","originURL":""},{"id":"9pdy0at","geo":[35.472089,139.610204],"priority":22,"name":"神奈川県立横浜翠嵐高等学校 正门","isFolder":false,"folder":"翠岚高-横滨市","uid":2168,"image":"/images/points/525565/9pdy0at_1768136472494.jpg","ep":1,"s":"","mark":"【此处属于学校地产，未经许可请勿入内】学院原型与取材地，神奈川县最好的公立学校，偏差值75，全国第23位。","density":12,"origin":"@甜食伯爵","originURL":""},{"id":"9pds2w9","geo":[35.472462,139.610173],"priority":5,"name":"神奈川県立横浜翠嵐高等学校 翠泉","isFolder":false,"folder":"翠岚高-横滨市","uid":2168,"image":"/images/points/525565/9pds2w9_1768136199530.jpg","ep":1,"s":"","mark":"【此处属于学校地产，未经许可请勿入内】学院原型与取材地，神奈川县最好的公立学校，偏差值75，全国第23位。此处取景是位于学校中心名为翠泉的小池塘，周边种有紫藤树，非常适合学生午餐。","density":4,"origin":"@甜食伯爵","originURL":""},{"id":"9pe6nc6","geo":[35.472467,139.610134],"priority":3,"name":"神奈川県立横浜翠嵐高等学校 翠泉","isFolder":false,"folder":"翠岚高-横滨市","uid":2168,"image":"/images/points/525565/9pe6nc6_1768136881289.jpg","ep":1,"s":"","mark":"【此处属于学校地产，未经许可请勿入内】学院原型与取材地，神奈川县最好的公立学校，偏差值75，全国第23位。此处取景是位于学校中心名为翠泉的小池塘，周边种有紫藤树，非常适合学生午餐。","density":3,"origin":"@甜食伯爵","originURL":""},{"id":"9pda5xa","geo":[35.472443,139.61014],"priority":4,"name":"神奈川県立横浜翠嵐高等学校 翠泉","isFolder":false,"folder":"翠岚高-横滨市","uid":2168,"image":"/images/points/525565/9pda5xa_1768135522708.jpg","ep":1,"s":"","mark":"【此处属于学校地产，未经许可请勿入内】学院原型与取材地，神奈川县最好的公立学校，偏差值75，全国第23位。此处取景是位于学校中心名为翠泉的小池塘，周边种有紫藤树，非常适合学生午餐。","density":3,"origin":"@甜食伯爵","originURL":""},{"id":"9pdogiu","geo":[35.47243,139.610111],"priority":25,"name":"神奈川県立横浜翠嵐高等学校 翠泉","isFolder":false,"folder":"翠岚高-横滨市","uid":2168,"image":"/images/points/525565/9pdogiu_1768136031692.jpg","ep":1,"s":"","mark":"【此处属于学校地产，未经许可请勿入内】学院原型与取材地，神奈川县最好的公立学校，偏差值75，全国第23位。此处取景是位于学校中心名为翠泉的小池塘，周边种有紫藤树，非常适合学生午餐。","density":4,"origin":"@甜食伯爵","originURL":""},{"id":"9pcwmr0","geo":[35.472254,139.610313],"priority":1,"name":"神奈川県立横浜翠嵐高等学校 鞋柜","isFolder":false,"folder":"翠岚高-横滨市","uid":2168,"image":"/images/points/525565/9pcwmr0_1768134731372.jpg","ep":1,"s":"","mark":"【此处属于学校地产，未经许可请勿入内】学院原型与取材地，神奈川县最好的公立学校，偏差值75，全国第23位。","density":1,"origin":"@甜食伯爵","originURL":""},{"id":"9pe99m6","geo":[35.472264,139.610305],"priority":1,"name":"神奈川県立横浜翠嵐高等学校 鞋柜","isFolder":false,"folder":"翠岚高-横滨市","uid":2168,"image":"/images/points/525565/9pe99m6_1768136995256.jpg","ep":1,"s":"","mark":"【此处属于学校地产，未经许可请勿入内】学院原型与取材地，神奈川县最好的公立学校，偏差值75，全国第23位。","density":1,"origin":"@甜食伯爵","originURL":""},{"id":"9pdwp1o","geo":[35.472279,139.610271],"priority":3,"name":"神奈川県立横浜翠嵐高等学校 鞋柜","isFolder":false,"folder":"翠岚高-横滨市","uid":2168,"image":"/images/points/525565/9pdwp1o_1768136412929.jpg","ep":1,"s":"","mark":"【此处属于学校地产，未经许可请勿入内】学院原型与取材地，神奈川县最好的公立学校，偏差值75，全国第23位。","density":3,"origin":"@甜食伯爵","originURL":""},{"id":"9pdwxzt","geo":[35.472287,139.610294],"priority":3,"name":"神奈川県立横浜翠嵐高等学校 鞋柜","isFolder":false,"folder":"翠岚高-横滨市","uid":2168,"image":"/images/points/525565/9pdwxzt_1768136422899.jpg","ep":1,"s":"","mark":"【此处属于学校地产，未经许可请勿入内】学院原型与取材地，神奈川县最好的公立学校，偏差值75，全国第23位。","density":3,"origin":"@甜食伯爵","originURL":""},{"id":"9pdxawa","geo":[35.472294,139.610316],"priority":4,"name":"神奈川県立横浜翠嵐高等学校 鞋柜","isFolder":false,"folder":"翠岚高-横滨市","uid":2168,"image":"/images/points/525565/9pdxawa_1768136440771.jpg","ep":1,"s":"","mark":"【此处属于学校地产，未经许可请勿入内】学院原型与取材地，神奈川县最好的公立学校，偏差值75，全国第23位。","density":3,"origin":"@甜食伯爵","originURL":""},{"id":"9pdxhl8","geo":[35.472263,139.610316],"priority":1,"name":"神奈川県立横浜翠嵐高等学校 鞋柜","isFolder":false,"folder":"翠岚高-横滨市","uid":2168,"image":"/images/points/525565/9pdxhl8_1768136447539.jpg","ep":1,"s":"","mark":"【此处属于学校地产，未经许可请勿入内】学院原型与取材地，神奈川县最好的公立学校，偏差值75，全国第23位。","density":1,"origin":"@甜食伯爵","originURL":""},{"id":"9pdxoco","geo":[35.472259,139.610319],"priority":2,"name":"神奈川県立横浜翠嵐高等学校 鞋柜","isFolder":false,"folder":"翠岚高-横滨市","uid":2168,"image":"/images/points/525565/9pdxoco_1768136455075.jpg","ep":1,"s":"","mark":"【此处属于学校地产，未经许可请勿入内】学院原型与取材地，神奈川县最好的公立学校，偏差值75，全国第23位。","density":1,"origin":"@甜食伯爵","originURL":""},{"id":"9pdxs6f","geo":[35.472267,139.610313],"priority":1,"name":"神奈川県立横浜翠嵐高等学校 鞋柜","isFolder":false,"folder":"翠岚高-横滨市","uid":2168,"image":"/images/points/525565/9pdxs6f_1768136464944.jpg","ep":1,"s":"","mark":"【此处属于学校地产，未经许可请勿入内】学院原型与取材地，神奈川县最好的公立学校，偏差值75，全国第23位。","density":1,"origin":"@甜食伯爵","originURL":""},{"id":"9pdx3mw","geo":[35.47226,139.610309],"priority":12,"name":"神奈川県立横浜翠嵐高等学校 鞋柜","isFolder":false,"folder":"翠岚高-横滨市","uid":2168,"image":"/images/points/525565/9pdx3mw_1768136431966.jpg","ep":1,"s":"","mark":"【此处属于学校地产，未经许可请勿入内】学院原型与取材地，神奈川县最好的公立学校，偏差值75，全国第23位。","density":1,"origin":"@甜食伯爵","originURL":""},{"id":"9pe6469","geo":[35.472351,139.610364],"priority":15,"name":"神奈川県立横浜翠嵐高等学校 鞋柜","isFolder":false,"folder":"翠岚高-横滨市","uid":2168,"image":"/images/points/525565/9pe6469_1768140958753.jpg","ep":1,"s":"","mark":"【此处属于学校地产，未经许可请勿入内】学院原型与取材地，神奈川县最好的公立学校，偏差值75，全国第23位。","density":8,"origin":"@甜食伯爵","originURL":""},{"id":"9pdri33","geo":[35.47265,139.610246],"priority":3,"name":"神奈川県立横浜翠嵐高等学校 走廊","isFolder":false,"folder":"翠岚高-横滨市","uid":2168,"image":"/images/points/525565/9pdri33_1768136168806.jpg","ep":1,"s":"","mark":"【此处属于学校地产，未经许可请勿入内】学院原型与取材地，神奈川县最好的公立学校，偏差值75，全国第23位。","density":2,"origin":"@甜食伯爵","originURL":""},{"id":"9pdhemd","geo":[35.472634,139.610203],"priority":3,"name":"神奈川県立横浜翠嵐高等学校 走廊","isFolder":false,"folder":"翠岚高-横滨市","uid":2168,"image":"/images/points/525565/9pdhemd_1768135724678.jpg","ep":1,"s":"","mark":"【此处属于学校地产，未经许可请勿入内】学院原型与取材地，神奈川县最好的公立学校，偏差值75，全国第23位。","density":3,"origin":"@甜食伯爵","originURL":""},{"id":"9pe3o6z","geo":[35.472751,139.6104],"priority":3,"name":"神奈川県立横浜翠嵐高等学校 2F走廊","isFolder":false,"folder":"翠岚高-横滨市","uid":2168,"image":"/images/points/525565/9pe3o6z_1768136739325.jpg","ep":1,"s":"","mark":"【此处属于学校地产，未经许可请勿入内】学院原型与取材地，神奈川县最好的公立学校，偏差值75，全国第23位。","density":2,"origin":"@甜食伯爵","originURL":""},{"id":"9pe48ce","geo":[35.472743,139.610382],"priority":5,"name":"神奈川県立横浜翠嵐高等学校 2F走廊","isFolder":false,"folder":"翠岚高-横滨市","uid":2168,"image":"/images/points/525565/9pe48ce_1768136765418.jpg","ep":1,"s":"","mark":"【此处属于学校地产，未经许可请勿入内】学院原型与取材地，神奈川县最好的公立学校，偏差值75，全国第23位。","density":2,"origin":"@甜食伯爵","originURL":""},{"id":"9pe40kx","geo":[35.472759,139.610424],"priority":4,"name":"神奈川県立横浜翠嵐高等学校 2F走廊","isFolder":false,"folder":"翠岚高-横滨市","uid":2168,"image":"/images/points/525565/9pe40kx_1768136753696.jpg","ep":1,"s":"","mark":"【此处属于学校地产，未经许可请勿入内】学院原型与取材地，神奈川县最好的公立学校，偏差值75，全国第23位。","density":3,"origin":"@甜食伯爵","originURL":""},{"id":"9pdn0wr","geo":[35.472645,139.610227],"priority":23,"name":"神奈川県立横浜翠嵐高等学校 走廊","isFolder":false,"folder":"翠岚高-横滨市","uid":2168,"image":"/images/points/525565/9pdn0wr_1768135958865.jpg","ep":1,"s":"","mark":"【此处属于学校地产，未经许可请勿入内】学院原型与取材地，神奈川县最好的公立学校，偏差值75，全国第23位。","density":2,"origin":"@甜食伯爵","originURL":""},{"id":"9pe4oy6","geo":[35.472406,139.610504],"priority":11,"name":"神奈川県立横浜翠嵐高等学校 1F走廊","isFolder":false,"folder":"翠岚高-横滨市","uid":2168,"image":"/images/points/525565/9pe4oy6_1768136794692.jpg","ep":1,"s":"","mark":"【此处属于学校地产，未经许可请勿入内】学院原型与取材地，神奈川县最好的公立学校，偏差值75，全国第23位。","density":10,"origin":"@甜食伯爵","originURL":""},{"id":"9pe4gih","geo":[35.472467,139.610422],"priority":3,"name":"神奈川県立横浜翠嵐高等学校 台阶","isFolder":false,"folder":"翠岚高-横滨市","uid":2168,"image":"/images/points/525565/9pe4gih_1768136773843.jpg","ep":1,"s":"","mark":"【此处属于学校地产，未经许可请勿入内】学院原型与取材地，神奈川县最好的公立学校，偏差值75，全国第23位。","density":2,"origin":"@甜食伯爵","originURL":""},{"id":"9pdi5t6","geo":[35.472475,139.610442],"priority":35,"name":"神奈川県立横浜翠嵐高等学校 台阶","isFolder":false,"folder":"翠岚高-横滨市","uid":2168,"image":"/images/points/525565/9pdi5t6_1768135732430.jpg","ep":1,"s":"","mark":"【此处属于学校地产，未经许可请勿入内】学院原型与取材地，神奈川县最好的公立学校，偏差值75，全国第23位。","density":2,"origin":"@甜食伯爵","originURL":""},{"id":"9pdif69","geo":[35.472793,139.610384],"priority":2,"name":"神奈川県立横浜翠嵐高等学校 教室","isFolder":false,"folder":"翠岚高-横滨市","uid":2168,"image":"/images/points/525565/9pdif69_1768135743430.jpg","ep":1,"s":"","mark":"【此处属于学校地产，未经许可请勿入内】学院原型与取材地，神奈川县最好的公立学校，偏差值75，全国第23位。","density":1,"origin":"@甜食伯爵","originURL":""},{"id":"9pdzex1","geo":[35.472787,139.610412],"priority":3,"name":"神奈川県立横浜翠嵐高等学校 教室","isFolder":false,"folder":"翠岚高-横滨市","uid":2168,"image":"/images/points/525565/9pdzex1_1768136542820.jpg","ep":1,"s":"","mark":"【此处属于学校地产，未经许可请勿入内】学院原型与取材地，神奈川县最好的公立学校，偏差值75，全国第23位。","density":2,"origin":"@甜食伯爵","originURL":""},{"id":"9pdzpcm","geo":[35.472814,139.610416],"priority":2,"name":"神奈川県立横浜翠嵐高等学校 教室","isFolder":false,"folder":"翠岚高-横滨市","uid":2168,"image":"/images/points/525565/9pdzpcm_1768136554960.jpg","ep":1,"s":"","mark":"【此处属于学校地产，未经许可请勿入内】学院原型与取材地，神奈川县最好的公立学校，偏差值75，全国第23位。","density":2,"origin":"@甜食伯爵","originURL":""},{"id":"9pdukxc","geo":[35.472847,139.610358],"priority":6,"name":"神奈川県立横浜翠嵐高等学校 教室","isFolder":false,"folder":"翠岚高-横滨市","uid":2168,"image":"/images/points/525565/9pdukxc_1768136315419.jpg","ep":1,"s":"","mark":"【此处属于学校地产，未经许可请勿入内】学院原型与取材地，神奈川县最好的公立学校，偏差值75，全国第23位。","density":6,"origin":"@甜食伯爵","originURL":""},{"id":"9pdrbhv","geo":[35.472808,139.610403],"priority":2,"name":"神奈川県立横浜翠嵐高等学校 教室","isFolder":false,"folder":"翠岚高-横滨市","uid":2168,"image":"/images/points/525565/9pdrbhv_1768136160691.jpg","ep":1,"s":"","mark":"【此处属于学校地产，未经许可请勿入内】学院原型与取材地，神奈川县最好的公立学校，偏差值75，全国第23位。","density":2,"origin":"@甜食伯爵","originURL":""},{"id":"9pditlu","geo":[35.472787,139.610371],"priority":1,"name":"神奈川県立横浜翠嵐高等学校 教室","isFolder":false,"folder":"翠岚高-横滨市","uid":2168,"image":"/images/points/525565/9pditlu_1768135764899.jpg","ep":1,"s":"","mark":"【此处属于学校地产，未经许可请勿入内】学院原型与取材地，神奈川县最好的公立学校，偏差值75，全国第23位。","density":1,"origin":"@甜食伯爵","originURL":""},{"id":"9pdj10x","geo":[35.472795,139.610368],"priority":2,"name":"神奈川県立横浜翠嵐高等学校 教室","isFolder":false,"folder":"翠岚高-横滨市","uid":2168,"image":"/images/points/525565/9pdj10x_1768135772524.jpg","ep":1,"s":"","mark":"【此处属于学校地产，未经许可请勿入内】学院原型与取材地，神奈川县最好的公立学校，偏差值75，全国第23位。","density":1,"origin":"@甜食伯爵","originURL":""},{"id":"9pdj5ps","geo":[35.472804,139.610389],"priority":2,"name":"神奈川県立横浜翠嵐高等学校 教室","isFolder":false,"folder":"翠岚高-横滨市","uid":2168,"image":"/images/points/525565/9pdj5ps_1768135777605.jpg","ep":1,"s":"","mark":"【此处属于学校地产，未经许可请勿入内】学院原型与取材地，神奈川县最好的公立学校，偏差值75，全国第23位。","density":1,"origin":"@甜食伯爵","originURL":""},{"id":"9pdj99e","geo":[35.472796,139.610394],"priority":2,"name":"神奈川県立横浜翠嵐高等学校 教室","isFolder":false,"folder":"翠岚高-横滨市","uid":2168,"image":"/images/points/525565/9pdj99e_1768135800593.jpg","ep":1,"s":"","mark":"【此处属于学校地产，未经许可请勿入内】学院原型与取材地，神奈川县最好的公立学校，偏差值75，全国第23位。","density":1,"origin":"@甜食伯爵","originURL":""},{"id":"9pdinbq","geo":[35.472801,139.610379],"priority":15,"name":"神奈川県立横浜翠嵐高等学校 教室","isFolder":false,"folder":"翠岚高-横滨市","uid":2168,"image":"/images/points/525565/9pdinbq_1768135753647.jpg","ep":1,"s":"","mark":"【此处属于学校地产，未经许可请勿入内】学院原型与取材地，神奈川县最好的公立学校，偏差值75，全国第23位。","density":1,"origin":"@甜食伯爵","originURL":""},{"id":"9pdzz7j","geo":[35.473104,139.610211],"priority":4,"name":"神奈川県立横浜翠嵐高等学校 教室","isFolder":false,"folder":"翠岚高-横滨市","uid":2168,"image":"/images/points/525565/9pdzz7j_1768136572231.jpg","ep":1,"s":"","mark":"【此处属于学校地产，未经许可请勿入内】学院原型与取材地，神奈川县最好的公立学校，偏差值75，全国第23位。","density":3,"origin":"@甜食伯爵","originURL":""},{"id":"9pe0gct","geo":[35.473114,139.610237],"priority":3,"name":"神奈川県立横浜翠嵐高等学校 教室","isFolder":false,"folder":"翠岚高-横滨市","uid":2168,"image":"/images/points/525565/9pe0gct_1768136589338.jpg","ep":1,"s":"","mark":"【此处属于学校地产，未经许可请勿入内】学院原型与取材地，神奈川县最好的公立学校，偏差值75，全国第23位。","density":3,"origin":"@甜食伯爵","originURL":""},{"id":"9pe0nr7","geo":[35.473125,139.610264],"priority":4,"name":"神奈川県立横浜翠嵐高等学校 教室","isFolder":false,"folder":"翠岚高-横滨市","uid":2168,"image":"/images/points/525565/9pe0nr7_1768136601747.jpg","ep":1,"s":"","mark":"【此处属于学校地产，未经许可请勿入内】学院原型与取材地，神奈川县最好的公立学校，偏差值75，全国第23位。","density":3,"origin":"@甜食伯爵","originURL":""},{"id":"9pe0yo6","geo":[35.473094,139.610248],"priority":40,"name":"神奈川県立横浜翠嵐高等学校 教室","isFolder":false,"folder":"翠岚高-横滨市","uid":2168,"image":"/images/points/525565/9pe0yo6_1768136609341.jpg","ep":1,"s":"","mark":"【此处属于学校地产，未经许可请勿入内】学院原型与取材地，神奈川县最好的公立学校，偏差值75，全国第23位。","density":3,"origin":"@甜食伯爵","originURL":""},{"id":"9pdvk5d","geo":[35.47285,139.610504],"priority":1,"name":"神奈川県立横浜翠嵐高等学校 洗手间","isFolder":false,"folder":"翠岚高-横滨市","uid":2168,"image":"/images/points/525565/9pdvk5d_1768136360359.jpg","ep":1,"s":"","mark":"【此处属于学校地产，未经许可请勿入内】学院原型与取材地，神奈川县最好的公立学校，偏差值75，全国第23位。","origin":"@甜食伯爵","originURL":""},{"id":"9pdw1kz","geo":[35.472853,139.610512],"priority":1,"name":"神奈川県立横浜翠嵐高等学校 洗手间","isFolder":false,"folder":"翠岚高-横滨市","uid":2168,"image":"/images/points/525565/9pdw1kz_1768136385755.jpg","ep":1,"s":"","mark":"【此处属于学校地产，未经许可请勿入内】学院原型与取材地，神奈川县最好的公立学校，偏差值75，全国第23位。","origin":"@甜食伯爵","originURL":""},{"id":"9pdwc53","geo":[35.472852,139.610508],"priority":118,"name":"神奈川県立横浜翠嵐高等学校 洗手间","isFolder":false,"folder":"翠岚高-横滨市","uid":2168,"image":"/images/points/525565/9pdwc53_1768136393341.jpg","ep":1,"s":"","mark":"【此处属于学校地产，未经许可请勿入内】学院原型与取材地，神奈川县最好的公立学校，偏差值75，全国第23位。","origin":"@甜食伯爵","originURL":""},{"id":"9pdjtkx","geo":[35.47226,139.609614],"priority":24,"name":"神奈川県立横浜翠嵐高等学校 校内","isFolder":false,"folder":"翠岚高-横滨市","uid":2168,"image":"/images/points/525565/9pdjtkx_1768135809680.jpg","ep":1,"s":"","mark":"【此处属于学校地产，未经许可请勿入内】学院原型与取材地，神奈川县最好的公立学校，偏差值75，全国第23位。","density":23,"origin":"@甜食伯爵","originURL":""},{"id":"9pdq8t2","geo":[35.472105,139.609753],"priority":80,"name":"神奈川県立横浜翠嵐高等学校 图书室","isFolder":false,"folder":"翠岚高-横滨市","uid":2168,"image":"/images/points/525565/9pdq8t2_1768136108421.jpg","ep":1,"s":"","mark":"【此处属于学校地产，未经许可请勿入内】学院原型与取材地，神奈川县最好的公立学校，偏差值75，全国第23位。","density":23,"origin":"@甜食伯爵","originURL":""},{"id":"9pdnd3f","geo":[35.47282,139.609362],"priority":4,"name":"神奈川県立横浜翠嵐高等学校 体育馆","isFolder":false,"folder":"翠岚高-横滨市","uid":2168,"image":"/images/points/525565/9pdnd3f_1768135975089.jpg","ep":1,"s":"","mark":"【此处属于学校地产，未经许可请勿入内】学院原型与取材地，神奈川县最好的公立学校，偏差值75，全国第23位。","density":3,"origin":"@甜食伯爵","originURL":""},{"id":"9pdsytx","geo":[35.472781,139.609384],"priority":6,"name":"神奈川県立横浜翠嵐高等学校 体育馆","isFolder":false,"folder":"翠岚高-横滨市","uid":2168,"image":"/images/points/525565/9pdsytx_1768136237759.jpg","ep":1,"s":"","mark":"【此处属于学校地产，未经许可请勿入内】学院原型与取材地，神奈川县最好的公立学校，偏差值75，全国第23位。","density":5,"origin":"@甜食伯爵","originURL":""},{"id":"9pdtnts","geo":[35.472741,139.609414],"priority":11,"name":"神奈川県立横浜翠嵐高等学校 体育馆","isFolder":false,"folder":"翠岚高-横滨市","uid":2168,"image":"/images/points/525565/9pdtnts_1768136270591.jpg","ep":1,"s":"","mark":"【此处属于学校地产，未经许可请勿入内】学院原型与取材地，神奈川县最好的公立学校，偏差值75，全国第23位。","density":6,"origin":"@甜食伯爵","originURL":""},{"id":"9pe1514","geo":[35.472833,139.60939],"priority":52,"name":"神奈川県立横浜翠嵐高等学校 体育馆","isFolder":false,"folder":"翠岚高-横滨市","uid":2168,"image":"/images/points/525565/9pe1514_1768136623531.jpg","ep":1,"s":"","mark":"【此处属于学校地产，未经许可请勿入内】学院原型与取材地，神奈川县最好的公立学校，偏差值75，全国第23位。","density":3,"origin":"@甜食伯爵","originURL":""},{"id":"9pdmovh","geo":[35.47214,139.608927],"priority":8,"name":"神奈川県立横浜翠嵐高等学校 运动场","isFolder":false,"folder":"翠岚高-横滨市","uid":2168,"image":"/images/points/525565/9pdmovh_1768135943785.jpg","ep":1,"s":"","mark":"【此处属于学校地产，未经许可请勿入内】学院原型与取材地，神奈川县最好的公立学校，偏差值75，全国第23位。","density":8,"origin":"@甜食伯爵","originURL":""},{"id":"9pdu8kh","geo":[35.472567,139.609005],"priority":46,"name":"神奈川県立横浜翠嵐高等学校 运动场","isFolder":false,"folder":"翠岚高-横滨市","uid":2168,"image":"/images/points/525565/9pdu8kh_1768136301212.jpg","ep":1,"s":"","mark":"【此处属于学校地产，未经许可请勿入内】学院原型与取材地，神奈川县最好的公立学校，偏差值75，全国第23位。","density":45,"origin":"@甜食伯爵","originURL":""},{"id":"9pdr3fv","geo":[35.472159,139.608996],"priority":1462,"name":"神奈川県立横浜翠嵐高等学校 运动场","isFolder":false,"folder":"翠岚高-横滨市","uid":2168,"image":"/images/points/525565/9pdr3fv_1768136150109.jpg","ep":1,"s":"","mark":"【此处属于学校地产，未经许可请勿入内】学院原型与取材地，神奈川县最好的公立学校，偏差值75，全国第23位。","density":8,"origin":"@甜食伯爵","originURL":""},{"id":"bl5z9xr","geo":[35.56699,139.553854],"priority":8,"name":"山内図書館","isFolder":false,"folder":"山内図書館・山内地区センター-横浜市","image":"/images/user/0/bangumi/525565/points/bl5z9xr-1772234813130.jpg","ep":"5","s":"16:18","origin":"","originURL":""},{"id":"bl69ip0","geo":[35.566839,139.553819],"priority":25,"name":"山内図書館","isFolder":false,"folder":"山内図書館・山内地区センター-横浜市","image":"/images/user/0/bangumi/525565/points/bl69ip0-1772235285386.jpg","ep":"5","s":"16:32","origin":"","originURL":""},{"id":"bl6du7n","geo":[35.567136,139.553878],"priority":5,"name":"山内地区センター前交差点","isFolder":false,"folder":"山内図書館・山内地区センター-横浜市","image":"/images/user/0/bangumi/525565/points/bl6du7n-1772235483250.jpg","ep":"5","s":"16:44","origin":"","originURL":""},{"id":"bl6g694","geo":[35.567057,139.55386],"priority":5,"name":"あざみ野の河津桜","isFolder":false,"folder":"山内図書館・山内地区センター-横浜市","image":"/images/user/0/bangumi/525565/points/bl6g694-1772235595121.jpg","ep":"5","s":"16:55","origin":"","originURL":""},{"id":"bl6c4p0","geo":[35.567096,139.553872],"priority":139,"name":"山内地区センター","isFolder":false,"folder":"山内図書館・山内地区センター-横浜市","image":"/images/user/0/bangumi/525565/points/bl6c4p0-1772235402875.jpg","ep":"5","s":"16:41","origin":"","originURL":""},{"id":"dx153nu","geo":[35.71649,139.776282],"priority":183,"name":" 东京国立科学博物馆","cn":"东京国立科学博物馆","isFolder":false,"image":"/images/user/0/bangumi/525565/points/dx153nu-1777305862414.jpg","ep":"第九集","s":"15：12","origin":"","originURL":""},{"id":"dyfj9lg","geo":[35.444089,139.647976],"priority":263,"name":"横滨中华街朝阳门","isFolder":false,"image":"/images/user/0/bangumi/525565/points/dyfj9lg-1777390495617.jpg","ep":"12","s":"7：46","origin":"","originURL":""},{"id":"e9ccj94","geo":[35.565854,139.553797],"priority":3002,"name":"あざみ野南橋","isFolder":false,"folder":"山内図書館・山内地区センター-横浜市","image":"/images/user/0/bangumi/525565/points/e9ccj94-1778052354422.jpg","ep":"5","s":"16:10","origin":"","originURL":""},{"id":"fapr9qx","geo":[35.452454,139.647967],"priority":18,"name":"大さん橋","cn":"大栈桥展望","isFolder":false,"image":"/images/user/0/bangumi/525565/points/fapr9qx-1780310019529.jpg","s":"","mark":"小情侣站这里地上有路标","origin":"","originURL":""}],"tags":[],"priority":999,"icon":null,"tAbbr":"正反対","theme":{"src":"/images/ptheme/525565_100_76.webp?v=hjmfu","ids":["9pfzgls","9pft9x1","9pfs2jc","9pfxqz3","9pftujr","9pfwyfr","9pfxxtv","9pfznkl","9pftmp3","9pfzz2g","9pg0qh3","9pfuo2q","9pfz21w","9pftfnv","9pft26j","9pfyrzs","9pfxb76","9pfu6q8","9pfrhg5","9pfuv03","9pfrvkl","9pfy8go","9pfyf6f","9pfylrt","9pfzsrc","9pfz67i","9pg08wr","9pfsc64","9pg0inw","9pfsmq9","9pfv6rb","9pfwn6r","9pfvglu","9pfvrva","9pfvmkw","9pbyi5r","9pdnslh","9pe1jh9","9pdy0at","9pds2w9","9pe6nc6","9pda5xa","9pdogiu","9pcwmr0","9pe99m6","9pdwp1o","9pdwxzt","9pdxawa","9pdxhl8","9pdxoco","9pdxs6f","9pdx3mw","9pe6469","9pdri33","9pdhemd","9pe3o6z","9pe48ce","9pe40kx","9pdn0wr","9pe4oy6","9pe4gih","9pdi5t6","9pdif69","9pdzex1","9pdzpcm","9pdukxc","9pdrbhv","9pditlu","9pdj10x","9pdj5ps","9pdj99e","9pdinbq","9pdzz7j","9pe0gct","9pe0nr7","9pe0yo6","9pdvk5d","9pdw1kz","9pdwc53","9pdjtkx","9pdq8t2","9pdnd3f","9pdsytx","9pdtnts","9pe1514","9pdmovh","9pdu8kh","9pdr3fv"],"modified":1768141093818,"w":100,"h":76},"modified":1780540834531,"pointsLength":97,"imagesLength":97},"points":[{"id":"9pfzgls","geo":[35.560983,139.552905],"priority":3,"name":"赤田東公園 西侧","isFolder":false,"folder":"赤田东公园-横滨市","uid":2168,"image":"/images/points/525565/9pfzgls_1768139902256.jpg","ep":1,"s":"","density":2,"origin":"@甜食伯爵","originURL":""},{"id":"9pft9x1","geo":[35.561076,139.552899],"priority":4,"name":"赤田東公園 西侧","isFolder":false,"folder":"赤田东公园-横滨市","uid":2168,"image":"/images/points/525565/9pft9x1_1768139611532.jpg","ep":1,"s":"","density":3,"origin":"@甜食伯爵","originURL":""},{"id":"9pfs2jc","geo":[35.560859,139.552866],"priority":3,"name":"赤田東公園 西侧","isFolder":false,"folder":"赤田东公园-横滨市","uid":2168,"image":"/images/points/525565/9pfs2jc_1768139574187.jpg","ep":1,"s":"","density":3,"origin":"@甜食伯爵","originURL":""},{"id":"9pfxqz3","geo":[35.560831,139.552792],"priority":4,"name":"赤田東公園 西侧","isFolder":false,"folder":"赤田东公园-横滨市","uid":2168,"image":"/images/points/525565/9pfxqz3_1768139821039.jpg","ep":1,"s":"","density":4,"origin":"@甜食伯爵","originURL":""},{"id":"9pftujr","geo":[35.561015,139.552863],"priority":3,"name":"赤田東公園 西侧","isFolder":false,"folder":"赤田东公园-横滨市","uid":2168,"image":"/images/points/525565/9pftujr_1768139668899.jpg","ep":1,"s":"","density":3,"origin":"@甜食伯爵","originURL":""},{"id":"9pfwyfr","geo":[35.560922,139.552794],"priority":4,"name":"赤田東公園 西侧","isFolder":false,"folder":"赤田东公园-横滨市","uid":2168,"image":"/images/points/525565/9pfwyfr_1768139809568.jpg","ep":1,"s":"","density":4,"origin":"@甜食伯爵","originURL":""},{"id":"9pfxxtv","geo":[35.560884,139.552869],"priority":4,"name":"赤田東公園 西侧","isFolder":false,"folder":"赤田东公园-横滨市","uid":2168,"image":"/images/points/525565/9pfxxtv_1768139835273.jpg","ep":1,"s":"","density":3,"origin":"@甜食伯爵","originURL":""},{"id":"9pfznkl","geo":[35.560988,139.552861],"priority":3,"name":"赤田東公園 西侧","isFolder":false,"folder":"赤田东公园-横滨市","uid":2168,"image":"/images/points/525565/9pfznkl_1768139909012.jpg","ep":1,"s":"","density":2,"origin":"@甜食伯爵","originURL":""},{"id":"9pftmp3","geo":[35.561115,139.552907],"priority":4,"name":"赤田東公園 西侧","isFolder":false,"folder":"赤田东公园-横滨市","uid":2168,"image":"/images/points/525565/9pftmp3_1768139630558.jpg","ep":1,"s":"","density":4,"origin":"@甜食伯爵","originURL":""},{"id":"9pfzz2g","geo":[35.56104,139.552928],"priority":4,"name":"赤田東公園 西侧","isFolder":false,"folder":"赤田东公园-横滨市","uid":2168,"image":"/images/points/525565/9pfzz2g_1768139928830.jpg","ep":1,"s":"","density":3,"origin":"@甜食伯爵","originURL":""},{"id":"9pg0qh3","geo":[35.560918,139.552844],"priority":3,"name":"赤田東公園 西侧","isFolder":false,"folder":"赤田东公园-横滨市","uid":2168,"image":"/images/points/525565/9pg0qh3_1768139958244.jpg","ep":1,"s":"","density":3,"origin":"@甜食伯爵","originURL":""},{"id":"9pfuo2q","geo":[35.561048,139.552895],"priority":4,"name":"赤田東公園 西侧","isFolder":false,"folder":"赤田东公园-横滨市","uid":2168,"image":"/images/points/525565/9pfuo2q_1768139677315.jpg","ep":1,"s":"","density":3,"origin":"@甜食伯爵","originURL":""},{"id":"9pfz21w","geo":[35.560912,139.552872],"priority":5,"name":"赤田東公園 西侧","isFolder":false,"folder":"赤田东公园-横滨市","uid":2168,"image":"/images/points/525565/9pfz21w_1768139879478.jpg","ep":1,"s":"","density":3,"origin":"@甜食伯爵","originURL":""},{"id":"9pftfnv","geo":[35.561078,139.552863],"priority":5,"name":"赤田東公園 西侧","isFolder":false,"folder":"赤田东公园-横滨市","uid":2168,"image":"/images/points/525565/9pftfnv_1768139621177.jpg","ep":1,"s":"","density":4,"origin":"@甜食伯爵","originURL":""},{"id":"9pft26j","geo":[35.560955,139.552849],"priority":4,"name":"赤田東公園 西侧","isFolder":false,"folder":"赤田东公园-横滨市","uid":2168,"image":"/images/points/525565/9pft26j_1768139601828.jpg","ep":1,"s":"","density":4,"origin":"@甜食伯爵","originURL":""},{"id":"9pfyrzs","geo":[35.560943,139.552904],"priority":3,"name":"赤田東公園 西侧","isFolder":false,"folder":"赤田东公园-横滨市","uid":2168,"image":"/images/points/525565/9pfyrzs_1768139874177.jpg","ep":1,"s":"","density":3,"origin":"@甜食伯爵","originURL":""},{"id":"9pfxb76","geo":[35.560926,139.552759],"priority":10,"name":"赤田東公園 西侧","isFolder":false,"folder":"赤田东公园-横滨市","uid":2168,"image":"/images/points/525565/9pfxb76_1768139802501.jpg","ep":1,"s":"","density":4,"origin":"@甜食伯爵","originURL":""},{"id":"9pfu6q8","geo":[35.561012,139.552929],"priority":4,"name":"赤田東公園 西侧","isFolder":false,"folder":"赤田东公园-横滨市","uid":2168,"image":"/images/points/525565/9pfu6q8_1768139657609.jpg","ep":1,"s":"","density":3,"origin":"@甜食伯爵","originURL":""},{"id":"9pfrhg5","geo":[35.560861,139.55283],"priority":4,"name":"赤田東公園 西侧","isFolder":false,"folder":"赤田东公园-横滨市","uid":2168,"image":"/images/points/525565/9pfrhg5_1768139536469.jpg","ep":1,"s":"","density":4,"origin":"@甜食伯爵","originURL":""},{"id":"9pfuv03","geo":[35.561094,139.552932],"priority":3,"name":"赤田東公園 西侧","isFolder":false,"folder":"赤田东公园-横滨市","uid":2168,"image":"/images/points/525565/9pfuv03_1768139683345.jpg","ep":1,"s":"","density":2,"origin":"@甜食伯爵","originURL":""},{"id":"9pfrvkl","geo":[35.560829,139.552826],"priority":5,"name":"赤田東公園 西侧","isFolder":false,"folder":"赤田东公园-横滨市","uid":2168,"image":"/images/points/525565/9pfrvkl_1768139545436.jpg","ep":1,"s":"","density":4,"origin":"@甜食伯爵","originURL":""},{"id":"9pfy8go","geo":[35.560892,139.552839],"priority":7,"name":"赤田東公園 西侧","isFolder":false,"folder":"赤田东公园-横滨市","uid":2168,"image":"/images/points/525565/9pfy8go_1768139843420.jpg","ep":1,"s":"","density":3,"origin":"@甜食伯爵","originURL":""},{"id":"9pfyf6f","geo":[35.560822,139.552891],"priority":4,"name":"赤田東公園 西侧","isFolder":false,"folder":"赤田东公园-横滨市","uid":2168,"image":"/images/points/525565/9pfyf6f_1768139853281.jpg","ep":1,"s":"","density":3,"origin":"@甜食伯爵","originURL":""},{"id":"9pfylrt","geo":[35.560869,139.552895],"priority":7,"name":"赤田東公園 西侧","isFolder":false,"folder":"赤田东公园-横滨市","uid":2168,"image":"/images/points/525565/9pfylrt_1768139860104.jpg","ep":1,"s":"","density":3,"origin":"@甜食伯爵","originURL":""},{"id":"9pfzsrc","geo":[35.560981,139.552926],"priority":6,"name":"赤田東公園 西侧","isFolder":false,"folder":"赤田东公园-横滨市","uid":2168,"image":"/images/points/525565/9pfzsrc_1768139916917.jpg","ep":1,"s":"","density":2,"origin":"@甜食伯爵","originURL":""},{"id":"9pfz67i","geo":[35.560984,139.55288],"priority":4,"name":"赤田東公園 西侧","isFolder":false,"folder":"赤田东公园-横滨市","uid":2168,"image":"/images/points/525565/9pfz67i_1768139889024.jpg","ep":1,"s":"","density":2,"origin":"@甜食伯爵","originURL":""},{"id":"9pg08wr","geo":[35.561038,139.552868],"priority":8,"name":"赤田東公園 西侧","isFolder":false,"folder":"赤田东公园-横滨市","uid":2168,"image":"/images/points/525565/9pg08wr_1768139941751.jpg","ep":1,"s":"","density":3,"origin":"@甜食伯爵","originURL":""},{"id":"9pfsc64","geo":[35.560823,139.552863],"priority":15,"name":"赤田東公園 西侧","isFolder":false,"folder":"赤田东公园-横滨市","uid":2168,"image":"/images/points/525565/9pfsc64_1768139567767.jpg","ep":1,"s":"","density":3,"origin":"@甜食伯爵","originURL":""},{"id":"9pg0inw","geo":[35.561073,139.552929],"priority":15,"name":"赤田東公園 西侧","isFolder":false,"folder":"赤田东公园-横滨市","uid":2168,"image":"/images/points/525565/9pg0inw_1768139950751.jpg","ep":1,"s":"","density":2,"origin":"@甜食伯爵","originURL":""},{"id":"9pfsmq9","geo":[35.560949,139.55288],"priority":132,"name":"赤田東公園 西侧","isFolder":false,"folder":"赤田东公园-横滨市","uid":2168,"image":"/images/points/525565/9pfsmq9_1768139581918.jpg","ep":1,"s":"","density":3,"origin":"@甜食伯爵","originURL":""},{"id":"9pfv6rb","geo":[35.562179,139.553098],"priority":6,"name":"赤田東公園 西北角","isFolder":false,"folder":"赤田东公园-横滨市","uid":2168,"image":"/images/points/525565/9pfv6rb_1768139705264.jpg","ep":1,"s":"","density":5,"origin":"@甜食伯爵","originURL":""},{"id":"9pfwn6r","geo":[35.562116,139.553087],"priority":13,"name":"赤田東公園 西北角","isFolder":false,"folder":"赤田东公园-横滨市","uid":2168,"image":"/images/points/525565/9pfwn6r_1768139766736.jpg","ep":1,"s":"","density":7,"origin":"@甜食伯爵","originURL":""},{"id":"9pfvglu","geo":[35.562344,139.55313],"priority":5,"name":"赤田東公園 西北角","isFolder":false,"folder":"赤田东公园-横滨市","uid":2168,"image":"/images/points/525565/9pfvglu_1768139714128.jpg","ep":1,"s":"","density":5,"origin":"@甜食伯爵","originURL":""},{"id":"9pfvrva","geo":[35.562386,139.55313],"priority":18,"name":"赤田東公園 西北角","isFolder":false,"folder":"赤田东公园-横滨市","uid":2168,"image":"/images/points/525565/9pfvrva_1768139727705.jpg","ep":1,"s":"","density":5,"origin":"@甜食伯爵","originURL":""},{"id":"9pfvmkw","geo":[35.562226,139.553104],"priority":410,"name":"赤田東公園 西北角","isFolder":false,"folder":"赤田东公园-横滨市","uid":2168,"image":"/images/points/525565/9pfvmkw_1768139719531.jpg","ep":1,"s":"","density":5,"origin":"@甜食伯爵","originURL":""},{"id":"9pbyi5r","geo":[35.471957,139.610327],"priority":21,"name":"神奈川県立横浜翠嵐高等学校 正门","isFolder":false,"folder":"翠岚高-横滨市","uid":2168,"image":"/images/points/525565/9pbyi5r_1768134471915.jpg","ep":1,"s":"","mark":"【此处属于学校地产，未经许可请勿入内】学院原型与取材地，神奈川县最好的公立学校，偏差值75，全国第23位。","density":20,"origin":"@甜食伯爵","originURL":""},{"id":"9pdnslh","geo":[35.47219,139.610355],"priority":9,"name":"神奈川県立横浜翠嵐高等学校 正门","isFolder":false,"folder":"翠岚高-横滨市","uid":2168,"image":"/images/points/525565/9pdnslh_1768135996330.jpg","ep":1,"s":"","mark":"【此处属于学校地产，未经许可请勿入内】学院原型与取材地，神奈川县最好的公立学校，偏差值75，全国第23位。","density":8,"origin":"@甜食伯爵","originURL":""},{"id":"9pe1jh9","geo":[35.472169,139.610275],"priority":11,"name":"神奈川県立横浜翠嵐高等学校 正门","isFolder":false,"folder":"翠岚高-横滨市","uid":2168,"image":"/images/points/525565/9pe1jh9_1768136642710.jpg","ep":1,"s":"","mark":"【此处属于学校地产，未经许可请勿入内】学院原型与取材地，神奈川县最好的公立学校，偏差值75，全国第23位。","density":9,"origin":"@甜食伯爵","originURL":""},{"id":"9pdy0at","geo":[35.472089,139.610204],"priority":22,"name":"神奈川県立横浜翠嵐高等学校 正门","isFolder":false,"folder":"翠岚高-横滨市","uid":2168,"image":"/images/points/525565/9pdy0at_1768136472494.jpg","ep":1,"s":"","mark":"【此处属于学校地产，未经许可请勿入内】学院原型与取材地，神奈川县最好的公立学校，偏差值75，全国第23位。","density":12,"origin":"@甜食伯爵","originURL":""},{"id":"9pds2w9","geo":[35.472462,139.610173],"priority":5,"name":"神奈川県立横浜翠嵐高等学校 翠泉","isFolder":false,"folder":"翠岚高-横滨市","uid":2168,"image":"/images/points/525565/9pds2w9_1768136199530.jpg","ep":1,"s":"","mark":"【此处属于学校地产，未经许可请勿入内】学院原型与取材地，神奈川县最好的公立学校，偏差值75，全国第23位。此处取景是位于学校中心名为翠泉的小池塘，周边种有紫藤树，非常适合学生午餐。","density":4,"origin":"@甜食伯爵","originURL":""},{"id":"9pe6nc6","geo":[35.472467,139.610134],"priority":3,"name":"神奈川県立横浜翠嵐高等学校 翠泉","isFolder":false,"folder":"翠岚高-横滨市","uid":2168,"image":"/images/points/525565/9pe6nc6_1768136881289.jpg","ep":1,"s":"","mark":"【此处属于学校地产，未经许可请勿入内】学院原型与取材地，神奈川县最好的公立学校，偏差值75，全国第23位。此处取景是位于学校中心名为翠泉的小池塘，周边种有紫藤树，非常适合学生午餐。","density":3,"origin":"@甜食伯爵","originURL":""},{"id":"9pda5xa","geo":[35.472443,139.61014],"priority":4,"name":"神奈川県立横浜翠嵐高等学校 翠泉","isFolder":false,"folder":"翠岚高-横滨市","uid":2168,"image":"/images/points/525565/9pda5xa_1768135522708.jpg","ep":1,"s":"","mark":"【此处属于学校地产，未经许可请勿入内】学院原型与取材地，神奈川县最好的公立学校，偏差值75，全国第23位。此处取景是位于学校中心名为翠泉的小池塘，周边种有紫藤树，非常适合学生午餐。","density":3,"origin":"@甜食伯爵","originURL":""},{"id":"9pdogiu","geo":[35.47243,139.610111],"priority":25,"name":"神奈川県立横浜翠嵐高等学校 翠泉","isFolder":false,"folder":"翠岚高-横滨市","uid":2168,"image":"/images/points/525565/9pdogiu_1768136031692.jpg","ep":1,"s":"","mark":"【此处属于学校地产，未经许可请勿入内】学院原型与取材地，神奈川县最好的公立学校，偏差值75，全国第23位。此处取景是位于学校中心名为翠泉的小池塘，周边种有紫藤树，非常适合学生午餐。","density":4,"origin":"@甜食伯爵","originURL":""},{"id":"9pcwmr0","geo":[35.472254,139.610313],"priority":1,"name":"神奈川県立横浜翠嵐高等学校 鞋柜","isFolder":false,"folder":"翠岚高-横滨市","uid":2168,"image":"/images/points/525565/9pcwmr0_1768134731372.jpg","ep":1,"s":"","mark":"【此处属于学校地产，未经许可请勿入内】学院原型与取材地，神奈川县最好的公立学校，偏差值75，全国第23位。","density":1,"origin":"@甜食伯爵","originURL":""},{"id":"9pe99m6","geo":[35.472264,139.610305],"priority":1,"name":"神奈川県立横浜翠嵐高等学校 鞋柜","isFolder":false,"folder":"翠岚高-横滨市","uid":2168,"image":"/images/points/525565/9pe99m6_1768136995256.jpg","ep":1,"s":"","mark":"【此处属于学校地产，未经许可请勿入内】学院原型与取材地，神奈川县最好的公立学校，偏差值75，全国第23位。","density":1,"origin":"@甜食伯爵","originURL":""},{"id":"9pdwp1o","geo":[35.472279,139.610271],"priority":3,"name":"神奈川県立横浜翠嵐高等学校 鞋柜","isFolder":false,"folder":"翠岚高-横滨市","uid":2168,"image":"/images/points/525565/9pdwp1o_1768136412929.jpg","ep":1,"s":"","mark":"【此处属于学校地产，未经许可请勿入内】学院原型与取材地，神奈川县最好的公立学校，偏差值75，全国第23位。","density":3,"origin":"@甜食伯爵","originURL":""},{"id":"9pdwxzt","geo":[35.472287,139.610294],"priority":3,"name":"神奈川県立横浜翠嵐高等学校 鞋柜","isFolder":false,"folder":"翠岚高-横滨市","uid":2168,"image":"/images/points/525565/9pdwxzt_1768136422899.jpg","ep":1,"s":"","mark":"【此处属于学校地产，未经许可请勿入内】学院原型与取材地，神奈川县最好的公立学校，偏差值75，全国第23位。","density":3,"origin":"@甜食伯爵","originURL":""},{"id":"9pdxawa","geo":[35.472294,139.610316],"priority":4,"name":"神奈川県立横浜翠嵐高等学校 鞋柜","isFolder":false,"folder":"翠岚高-横滨市","uid":2168,"image":"/images/points/525565/9pdxawa_1768136440771.jpg","ep":1,"s":"","mark":"【此处属于学校地产，未经许可请勿入内】学院原型与取材地，神奈川县最好的公立学校，偏差值75，全国第23位。","density":3,"origin":"@甜食伯爵","originURL":""},{"id":"9pdxhl8","geo":[35.472263,139.610316],"priority":1,"name":"神奈川県立横浜翠嵐高等学校 鞋柜","isFolder":false,"folder":"翠岚高-横滨市","uid":2168,"image":"/images/points/525565/9pdxhl8_1768136447539.jpg","ep":1,"s":"","mark":"【此处属于学校地产，未经许可请勿入内】学院原型与取材地，神奈川县最好的公立学校，偏差值75，全国第23位。","density":1,"origin":"@甜食伯爵","originURL":""},{"id":"9pdxoco","geo":[35.472259,139.610319],"priority":2,"name":"神奈川県立横浜翠嵐高等学校 鞋柜","isFolder":false,"folder":"翠岚高-横滨市","uid":2168,"image":"/images/points/525565/9pdxoco_1768136455075.jpg","ep":1,"s":"","mark":"【此处属于学校地产，未经许可请勿入内】学院原型与取材地，神奈川县最好的公立学校，偏差值75，全国第23位。","density":1,"origin":"@甜食伯爵","originURL":""},{"id":"9pdxs6f","geo":[35.472267,139.610313],"priority":1,"name":"神奈川県立横浜翠嵐高等学校 鞋柜","isFolder":false,"folder":"翠岚高-横滨市","uid":2168,"image":"/images/points/525565/9pdxs6f_1768136464944.jpg","ep":1,"s":"","mark":"【此处属于学校地产，未经许可请勿入内】学院原型与取材地，神奈川县最好的公立学校，偏差值75，全国第23位。","density":1,"origin":"@甜食伯爵","originURL":""},{"id":"9pdx3mw","geo":[35.47226,139.610309],"priority":12,"name":"神奈川県立横浜翠嵐高等学校 鞋柜","isFolder":false,"folder":"翠岚高-横滨市","uid":2168,"image":"/images/points/525565/9pdx3mw_1768136431966.jpg","ep":1,"s":"","mark":"【此处属于学校地产，未经许可请勿入内】学院原型与取材地，神奈川县最好的公立学校，偏差值75，全国第23位。","density":1,"origin":"@甜食伯爵","originURL":""},{"id":"9pe6469","geo":[35.472351,139.610364],"priority":15,"name":"神奈川県立横浜翠嵐高等学校 鞋柜","isFolder":false,"folder":"翠岚高-横滨市","uid":2168,"image":"/images/points/525565/9pe6469_1768140958753.jpg","ep":1,"s":"","mark":"【此处属于学校地产，未经许可请勿入内】学院原型与取材地，神奈川县最好的公立学校，偏差值75，全国第23位。","density":8,"origin":"@甜食伯爵","originURL":""},{"id":"9pdri33","geo":[35.47265,139.610246],"priority":3,"name":"神奈川県立横浜翠嵐高等学校 走廊","isFolder":false,"folder":"翠岚高-横滨市","uid":2168,"image":"/images/points/525565/9pdri33_1768136168806.jpg","ep":1,"s":"","mark":"【此处属于学校地产，未经许可请勿入内】学院原型与取材地，神奈川县最好的公立学校，偏差值75，全国第23位。","density":2,"origin":"@甜食伯爵","originURL":""},{"id":"9pdhemd","geo":[35.472634,139.610203],"priority":3,"name":"神奈川県立横浜翠嵐高等学校 走廊","isFolder":false,"folder":"翠岚高-横滨市","uid":2168,"image":"/images/points/525565/9pdhemd_1768135724678.jpg","ep":1,"s":"","mark":"【此处属于学校地产，未经许可请勿入内】学院原型与取材地，神奈川县最好的公立学校，偏差值75，全国第23位。","density":3,"origin":"@甜食伯爵","originURL":""},{"id":"9pe3o6z","geo":[35.472751,139.6104],"priority":3,"name":"神奈川県立横浜翠嵐高等学校 2F走廊","isFolder":false,"folder":"翠岚高-横滨市","uid":2168,"image":"/images/points/525565/9pe3o6z_1768136739325.jpg","ep":1,"s":"","mark":"【此处属于学校地产，未经许可请勿入内】学院原型与取材地，神奈川县最好的公立学校，偏差值75，全国第23位。","density":2,"origin":"@甜食伯爵","originURL":""},{"id":"9pe48ce","geo":[35.472743,139.610382],"priority":5,"name":"神奈川県立横浜翠嵐高等学校 2F走廊","isFolder":false,"folder":"翠岚高-横滨市","uid":2168,"image":"/images/points/525565/9pe48ce_1768136765418.jpg","ep":1,"s":"","mark":"【此处属于学校地产，未经许可请勿入内】学院原型与取材地，神奈川县最好的公立学校，偏差值75，全国第23位。","density":2,"origin":"@甜食伯爵","originURL":""},{"id":"9pe40kx","geo":[35.472759,139.610424],"priority":4,"name":"神奈川県立横浜翠嵐高等学校 2F走廊","isFolder":false,"folder":"翠岚高-横滨市","uid":2168,"image":"/images/points/525565/9pe40kx_1768136753696.jpg","ep":1,"s":"","mark":"【此处属于学校地产，未经许可请勿入内】学院原型与取材地，神奈川县最好的公立学校，偏差值75，全国第23位。","density":3,"origin":"@甜食伯爵","originURL":""},{"id":"9pdn0wr","geo":[35.472645,139.610227],"priority":23,"name":"神奈川県立横浜翠嵐高等学校 走廊","isFolder":false,"folder":"翠岚高-横滨市","uid":2168,"image":"/images/points/525565/9pdn0wr_1768135958865.jpg","ep":1,"s":"","mark":"【此处属于学校地产，未经许可请勿入内】学院原型与取材地，神奈川县最好的公立学校，偏差值75，全国第23位。","density":2,"origin":"@甜食伯爵","originURL":""},{"id":"9pe4oy6","geo":[35.472406,139.610504],"priority":11,"name":"神奈川県立横浜翠嵐高等学校 1F走廊","isFolder":false,"folder":"翠岚高-横滨市","uid":2168,"image":"/images/points/525565/9pe4oy6_1768136794692.jpg","ep":1,"s":"","mark":"【此处属于学校地产，未经许可请勿入内】学院原型与取材地，神奈川县最好的公立学校，偏差值75，全国第23位。","density":10,"origin":"@甜食伯爵","originURL":""},{"id":"9pe4gih","geo":[35.472467,139.610422],"priority":3,"name":"神奈川県立横浜翠嵐高等学校 台阶","isFolder":false,"folder":"翠岚高-横滨市","uid":2168,"image":"/images/points/525565/9pe4gih_1768136773843.jpg","ep":1,"s":"","mark":"【此处属于学校地产，未经许可请勿入内】学院原型与取材地，神奈川县最好的公立学校，偏差值75，全国第23位。","density":2,"origin":"@甜食伯爵","originURL":""},{"id":"9pdi5t6","geo":[35.472475,139.610442],"priority":35,"name":"神奈川県立横浜翠嵐高等学校 台阶","isFolder":false,"folder":"翠岚高-横滨市","uid":2168,"image":"/images/points/525565/9pdi5t6_1768135732430.jpg","ep":1,"s":"","mark":"【此处属于学校地产，未经许可请勿入内】学院原型与取材地，神奈川县最好的公立学校，偏差值75，全国第23位。","density":2,"origin":"@甜食伯爵","originURL":""},{"id":"9pdif69","geo":[35.472793,139.610384],"priority":2,"name":"神奈川県立横浜翠嵐高等学校 教室","isFolder":false,"folder":"翠岚高-横滨市","uid":2168,"image":"/images/points/525565/9pdif69_1768135743430.jpg","ep":1,"s":"","mark":"【此处属于学校地产，未经许可请勿入内】学院原型与取材地，神奈川县最好的公立学校，偏差值75，全国第23位。","density":1,"origin":"@甜食伯爵","originURL":""},{"id":"9pdzex1","geo":[35.472787,139.610412],"priority":3,"name":"神奈川県立横浜翠嵐高等学校 教室","isFolder":false,"folder":"翠岚高-横滨市","uid":2168,"image":"/images/points/525565/9pdzex1_1768136542820.jpg","ep":1,"s":"","mark":"【此处属于学校地产，未经许可请勿入内】学院原型与取材地，神奈川县最好的公立学校，偏差值75，全国第23位。","density":2,"origin":"@甜食伯爵","originURL":""},{"id":"9pdzpcm","geo":[35.472814,139.610416],"priority":2,"name":"神奈川県立横浜翠嵐高等学校 教室","isFolder":false,"folder":"翠岚高-横滨市","uid":2168,"image":"/images/points/525565/9pdzpcm_1768136554960.jpg","ep":1,"s":"","mark":"【此处属于学校地产，未经许可请勿入内】学院原型与取材地，神奈川县最好的公立学校，偏差值75，全国第23位。","density":2,"origin":"@甜食伯爵","originURL":""},{"id":"9pdukxc","geo":[35.472847,139.610358],"priority":6,"name":"神奈川県立横浜翠嵐高等学校 教室","isFolder":false,"folder":"翠岚高-横滨市","uid":2168,"image":"/images/points/525565/9pdukxc_1768136315419.jpg","ep":1,"s":"","mark":"【此处属于学校地产，未经许可请勿入内】学院原型与取材地，神奈川县最好的公立学校，偏差值75，全国第23位。","density":6,"origin":"@甜食伯爵","originURL":""},{"id":"9pdrbhv","geo":[35.472808,139.610403],"priority":2,"name":"神奈川県立横浜翠嵐高等学校 教室","isFolder":false,"folder":"翠岚高-横滨市","uid":2168,"image":"/images/points/525565/9pdrbhv_1768136160691.jpg","ep":1,"s":"","mark":"【此处属于学校地产，未经许可请勿入内】学院原型与取材地，神奈川县最好的公立学校，偏差值75，全国第23位。","density":2,"origin":"@甜食伯爵","originURL":""},{"id":"9pditlu","geo":[35.472787,139.610371],"priority":1,"name":"神奈川県立横浜翠嵐高等学校 教室","isFolder":false,"folder":"翠岚高-横滨市","uid":2168,"image":"/images/points/525565/9pditlu_1768135764899.jpg","ep":1,"s":"","mark":"【此处属于学校地产，未经许可请勿入内】学院原型与取材地，神奈川县最好的公立学校，偏差值75，全国第23位。","density":1,"origin":"@甜食伯爵","originURL":""},{"id":"9pdj10x","geo":[35.472795,139.610368],"priority":2,"name":"神奈川県立横浜翠嵐高等学校 教室","isFolder":false,"folder":"翠岚高-横滨市","uid":2168,"image":"/images/points/525565/9pdj10x_1768135772524.jpg","ep":1,"s":"","mark":"【此处属于学校地产，未经许可请勿入内】学院原型与取材地，神奈川县最好的公立学校，偏差值75，全国第23位。","density":1,"origin":"@甜食伯爵","originURL":""},{"id":"9pdj5ps","geo":[35.472804,139.610389],"priority":2,"name":"神奈川県立横浜翠嵐高等学校 教室","isFolder":false,"folder":"翠岚高-横滨市","uid":2168,"image":"/images/points/525565/9pdj5ps_1768135777605.jpg","ep":1,"s":"","mark":"【此处属于学校地产，未经许可请勿入内】学院原型与取材地，神奈川县最好的公立学校，偏差值75，全国第23位。","density":1,"origin":"@甜食伯爵","originURL":""},{"id":"9pdj99e","geo":[35.472796,139.610394],"priority":2,"name":"神奈川県立横浜翠嵐高等学校 教室","isFolder":false,"folder":"翠岚高-横滨市","uid":2168,"image":"/images/points/525565/9pdj99e_1768135800593.jpg","ep":1,"s":"","mark":"【此处属于学校地产，未经许可请勿入内】学院原型与取材地，神奈川县最好的公立学校，偏差值75，全国第23位。","density":1,"origin":"@甜食伯爵","originURL":""},{"id":"9pdinbq","geo":[35.472801,139.610379],"priority":15,"name":"神奈川県立横浜翠嵐高等学校 教室","isFolder":false,"folder":"翠岚高-横滨市","uid":2168,"image":"/images/points/525565/9pdinbq_1768135753647.jpg","ep":1,"s":"","mark":"【此处属于学校地产，未经许可请勿入内】学院原型与取材地，神奈川县最好的公立学校，偏差值75，全国第23位。","density":1,"origin":"@甜食伯爵","originURL":""},{"id":"9pdzz7j","geo":[35.473104,139.610211],"priority":4,"name":"神奈川県立横浜翠嵐高等学校 教室","isFolder":false,"folder":"翠岚高-横滨市","uid":2168,"image":"/images/points/525565/9pdzz7j_1768136572231.jpg","ep":1,"s":"","mark":"【此处属于学校地产，未经许可请勿入内】学院原型与取材地，神奈川县最好的公立学校，偏差值75，全国第23位。","density":3,"origin":"@甜食伯爵","originURL":""},{"id":"9pe0gct","geo":[35.473114,139.610237],"priority":3,"name":"神奈川県立横浜翠嵐高等学校 教室","isFolder":false,"folder":"翠岚高-横滨市","uid":2168,"image":"/images/points/525565/9pe0gct_1768136589338.jpg","ep":1,"s":"","mark":"【此处属于学校地产，未经许可请勿入内】学院原型与取材地，神奈川县最好的公立学校，偏差值75，全国第23位。","density":3,"origin":"@甜食伯爵","originURL":""},{"id":"9pe0nr7","geo":[35.473125,139.610264],"priority":4,"name":"神奈川県立横浜翠嵐高等学校 教室","isFolder":false,"folder":"翠岚高-横滨市","uid":2168,"image":"/images/points/525565/9pe0nr7_1768136601747.jpg","ep":1,"s":"","mark":"【此处属于学校地产，未经许可请勿入内】学院原型与取材地，神奈川县最好的公立学校，偏差值75，全国第23位。","density":3,"origin":"@甜食伯爵","originURL":""},{"id":"9pe0yo6","geo":[35.473094,139.610248],"priority":40,"name":"神奈川県立横浜翠嵐高等学校 教室","isFolder":false,"folder":"翠岚高-横滨市","uid":2168,"image":"/images/points/525565/9pe0yo6_1768136609341.jpg","ep":1,"s":"","mark":"【此处属于学校地产，未经许可请勿入内】学院原型与取材地，神奈川县最好的公立学校，偏差值75，全国第23位。","density":3,"origin":"@甜食伯爵","originURL":""},{"id":"9pdvk5d","geo":[35.47285,139.610504],"priority":1,"name":"神奈川県立横浜翠嵐高等学校 洗手间","isFolder":false,"folder":"翠岚高-横滨市","uid":2168,"image":"/images/points/525565/9pdvk5d_1768136360359.jpg","ep":1,"s":"","mark":"【此处属于学校地产，未经许可请勿入内】学院原型与取材地，神奈川县最好的公立学校，偏差值75，全国第23位。","origin":"@甜食伯爵","originURL":""},{"id":"9pdw1kz","geo":[35.472853,139.610512],"priority":1,"name":"神奈川県立横浜翠嵐高等学校 洗手间","isFolder":false,"folder":"翠岚高-横滨市","uid":2168,"image":"/images/points/525565/9pdw1kz_1768136385755.jpg","ep":1,"s":"","mark":"【此处属于学校地产，未经许可请勿入内】学院原型与取材地，神奈川县最好的公立学校，偏差值75，全国第23位。","origin":"@甜食伯爵","originURL":""},{"id":"9pdwc53","geo":[35.472852,139.610508],"priority":118,"name":"神奈川県立横浜翠嵐高等学校 洗手间","isFolder":false,"folder":"翠岚高-横滨市","uid":2168,"image":"/images/points/525565/9pdwc53_1768136393341.jpg","ep":1,"s":"","mark":"【此处属于学校地产，未经许可请勿入内】学院原型与取材地，神奈川县最好的公立学校，偏差值75，全国第23位。","origin":"@甜食伯爵","originURL":""},{"id":"9pdjtkx","geo":[35.47226,139.609614],"priority":24,"name":"神奈川県立横浜翠嵐高等学校 校内","isFolder":false,"folder":"翠岚高-横滨市","uid":2168,"image":"/images/points/525565/9pdjtkx_1768135809680.jpg","ep":1,"s":"","mark":"【此处属于学校地产，未经许可请勿入内】学院原型与取材地，神奈川县最好的公立学校，偏差值75，全国第23位。","density":23,"origin":"@甜食伯爵","originURL":""},{"id":"9pdq8t2","geo":[35.472105,139.609753],"priority":80,"name":"神奈川県立横浜翠嵐高等学校 图书室","isFolder":false,"folder":"翠岚高-横滨市","uid":2168,"image":"/images/points/525565/9pdq8t2_1768136108421.jpg","ep":1,"s":"","mark":"【此处属于学校地产，未经许可请勿入内】学院原型与取材地，神奈川县最好的公立学校，偏差值75，全国第23位。","density":23,"origin":"@甜食伯爵","originURL":""},{"id":"9pdnd3f","geo":[35.47282,139.609362],"priority":4,"name":"神奈川県立横浜翠嵐高等学校 体育馆","isFolder":false,"folder":"翠岚高-横滨市","uid":2168,"image":"/images/points/525565/9pdnd3f_1768135975089.jpg","ep":1,"s":"","mark":"【此处属于学校地产，未经许可请勿入内】学院原型与取材地，神奈川县最好的公立学校，偏差值75，全国第23位。","density":3,"origin":"@甜食伯爵","originURL":""},{"id":"9pdsytx","geo":[35.472781,139.609384],"priority":6,"name":"神奈川県立横浜翠嵐高等学校 体育馆","isFolder":false,"folder":"翠岚高-横滨市","uid":2168,"image":"/images/points/525565/9pdsytx_1768136237759.jpg","ep":1,"s":"","mark":"【此处属于学校地产，未经许可请勿入内】学院原型与取材地，神奈川县最好的公立学校，偏差值75，全国第23位。","density":5,"origin":"@甜食伯爵","originURL":""},{"id":"9pdtnts","geo":[35.472741,139.609414],"priority":11,"name":"神奈川県立横浜翠嵐高等学校 体育馆","isFolder":false,"folder":"翠岚高-横滨市","uid":2168,"image":"/images/points/525565/9pdtnts_1768136270591.jpg","ep":1,"s":"","mark":"【此处属于学校地产，未经许可请勿入内】学院原型与取材地，神奈川县最好的公立学校，偏差值75，全国第23位。","density":6,"origin":"@甜食伯爵","originURL":""},{"id":"9pe1514","geo":[35.472833,139.60939],"priority":52,"name":"神奈川県立横浜翠嵐高等学校 体育馆","isFolder":false,"folder":"翠岚高-横滨市","uid":2168,"image":"/images/points/525565/9pe1514_1768136623531.jpg","ep":1,"s":"","mark":"【此处属于学校地产，未经许可请勿入内】学院原型与取材地，神奈川县最好的公立学校，偏差值75，全国第23位。","density":3,"origin":"@甜食伯爵","originURL":""},{"id":"9pdmovh","geo":[35.47214,139.608927],"priority":8,"name":"神奈川県立横浜翠嵐高等学校 运动场","isFolder":false,"folder":"翠岚高-横滨市","uid":2168,"image":"/images/points/525565/9pdmovh_1768135943785.jpg","ep":1,"s":"","mark":"【此处属于学校地产，未经许可请勿入内】学院原型与取材地，神奈川县最好的公立学校，偏差值75，全国第23位。","density":8,"origin":"@甜食伯爵","originURL":""},{"id":"9pdu8kh","geo":[35.472567,139.609005],"priority":46,"name":"神奈川県立横浜翠嵐高等学校 运动场","isFolder":false,"folder":"翠岚高-横滨市","uid":2168,"image":"/images/points/525565/9pdu8kh_1768136301212.jpg","ep":1,"s":"","mark":"【此处属于学校地产，未经许可请勿入内】学院原型与取材地，神奈川县最好的公立学校，偏差值75，全国第23位。","density":45,"origin":"@甜食伯爵","originURL":""},{"id":"9pdr3fv","geo":[35.472159,139.608996],"priority":1462,"name":"神奈川県立横浜翠嵐高等学校 运动场","isFolder":false,"folder":"翠岚高-横滨市","uid":2168,"image":"/images/points/525565/9pdr3fv_1768136150109.jpg","ep":1,"s":"","mark":"【此处属于学校地产，未经许可请勿入内】学院原型与取材地，神奈川县最好的公立学校，偏差值75，全国第23位。","density":8,"origin":"@甜食伯爵","originURL":""},{"id":"bl5z9xr","geo":[35.56699,139.553854],"priority":8,"name":"山内図書館","isFolder":false,"folder":"山内図書館・山内地区センター-横浜市","image":"/images/user/0/bangumi/525565/points/bl5z9xr-1772234813130.jpg","ep":"5","s":"16:18","origin":"","originURL":""},{"id":"bl69ip0","geo":[35.566839,139.553819],"priority":25,"name":"山内図書館","isFolder":false,"folder":"山内図書館・山内地区センター-横浜市","image":"/images/user/0/bangumi/525565/points/bl69ip0-1772235285386.jpg","ep":"5","s":"16:32","origin":"","originURL":""},{"id":"bl6du7n","geo":[35.567136,139.553878],"priority":5,"name":"山内地区センター前交差点","isFolder":false,"folder":"山内図書館・山内地区センター-横浜市","image":"/images/user/0/bangumi/525565/points/bl6du7n-1772235483250.jpg","ep":"5","s":"16:44","origin":"","originURL":""},{"id":"bl6g694","geo":[35.567057,139.55386],"priority":5,"name":"あざみ野の河津桜","isFolder":false,"folder":"山内図書館・山内地区センター-横浜市","image":"/images/user/0/bangumi/525565/points/bl6g694-1772235595121.jpg","ep":"5","s":"16:55","origin":"","originURL":""},{"id":"bl6c4p0","geo":[35.567096,139.553872],"priority":139,"name":"山内地区センター","isFolder":false,"folder":"山内図書館・山内地区センター-横浜市","image":"/images/user/0/bangumi/525565/points/bl6c4p0-1772235402875.jpg","ep":"5","s":"16:41","origin":"","originURL":""},{"id":"dx153nu","geo":[35.71649,139.776282],"priority":183,"name":" 东京国立科学博物馆","cn":"东京国立科学博物馆","isFolder":false,"image":"/images/user/0/bangumi/525565/points/dx153nu-1777305862414.jpg","ep":"第九集","s":"15：12","origin":"","originURL":""},{"id":"dyfj9lg","geo":[35.444089,139.647976],"priority":263,"name":"横滨中华街朝阳门","isFolder":false,"image":"/images/user/0/bangumi/525565/points/dyfj9lg-1777390495617.jpg","ep":"12","s":"7：46","origin":"","originURL":""},{"id":"e9ccj94","geo":[35.565854,139.553797],"priority":3002,"name":"あざみ野南橋","isFolder":false,"folder":"山内図書館・山内地区センター-横浜市","image":"/images/user/0/bangumi/525565/points/e9ccj94-1778052354422.jpg","ep":"5","s":"16:10","origin":"","originURL":""},{"id":"fapr9qx","geo":[35.452454,139.647967],"priority":18,"name":"大さん橋","cn":"大栈桥展望","isFolder":false,"image":"/images/user/0/bangumi/525565/points/fapr9qx-1780310019529.jpg","s":"","mark":"小情侣站这里地上有路标","origin":"","originURL":""}]}