{"version":1,"source":"indexeddb-geo2025-snapshot","modified":1782096381181,"work":{"id":95010,"cn":null,"title":"Free!-Eternal Summer-","cover":"http://bgm-api.anitabi.cn/pic/cover/l/c6/ec/95010_jE29x.jpg","fade":6.8,"cat":"TV","points":[{"id":"oii99h2zf","geo":[-33.860526,151.208354],"priority":6545325,"name":"The Russell Boutique Hotel","cn":"岩石区罗素酒店","isFolder":false,"image":"/images/user/0/bangumi/95010/points/n9bf0x9ff-1723759070121.jpg","ep":12,"s":"742","density":110999999889000,"origin":"","originURL":""}],"tags":[],"priority":999,"icon":"/images/icon/95010.jpg","theme":{"src":"/images/ptheme/95010.webp?v=h3s1l","ids":["n9bf0x9ff"],"modified":1723787112800},"modified":1723787112941,"pointsLength":1,"imagesLength":1},"points":[{"id":"oii99h2zf","geo":[-33.860526,151.208354],"priority":6545325,"name":"The Russell Boutique Hotel","cn":"岩石区罗素酒店","isFolder":false,"image":"/images/user/0/bangumi/95010/points/n9bf0x9ff-1723759070121.jpg","ep":12,"s":"742","density":110999999889000,"origin":"","originURL":""}]}